{
  "analysis": {
    "generatedAt": "2026-02-23T06:19:37.721Z",
    "totalCalls": 1200,
    "connectedCalls": 670,
    "avgDurationSec": 92.1,
    "medianDurationSec": 61,
    "bucketSummary": [
      {
        "bucket": "0s",
        "count": 530,
        "percent": 44.2
      },
      {
        "bucket": "<30s",
        "count": 194,
        "percent": 16.2
      },
      {
        "bucket": "60-120s",
        "count": 142,
        "percent": 11.8
      },
      {
        "bucket": "30-60s",
        "count": 138,
        "percent": 11.5
      },
      {
        "bucket": "120-180s",
        "count": 100,
        "percent": 8.3
      },
      {
        "bucket": "180-300s",
        "count": 70,
        "percent": 5.8
      },
      {
        "bucket": "300s+",
        "count": 26,
        "percent": 2.2
      }
    ],
    "statusSummary": [
      {
        "status": "Unattended Dialled",
        "count": 464,
        "percent": 38.7
      },
      {
        "status": "Received",
        "count": 345,
        "percent": 28.7
      },
      {
        "status": "Attended Dialled",
        "count": 325,
        "percent": 27.1
      },
      {
        "status": "Missed",
        "count": 66,
        "percent": 5.5
      }
    ],
    "typeSummary": [
      {
        "type": "Outbound",
        "count": 789,
        "percent": 65.8
      },
      {
        "type": "Inbound",
        "count": 345,
        "percent": 28.7
      },
      {
        "type": "Missed",
        "count": 66,
        "percent": 5.5
      }
    ],
    "totalTalkSeconds": 61707,
    "hourlyTalkSeconds": [
      0,
      0,
      0,
      0,
      0,
      0,
      0,
      0,
      2820,
      4855,
      9282,
      13233,
      10358,
      6060,
      2504,
      4131,
      2625,
      1291,
      1202,
      2074,
      1251,
      21,
      0,
      0
    ],
    "ownerSummary": [
      {
        "owner": "Rajeswari R",
        "totalCalls": 217,
        "connectedCalls": 94,
        "avgDurationSec": 83.7,
        "connectionRatePercent": 43.3,
        "avgBookingSeconds": 83.7,
        "peakHour": "11:00",
        "bucketBreakdown": [
          {
            "bucket": "0s",
            "count": 123,
            "percent": 56.7
          },
          {
            "bucket": "60-120s",
            "count": 30,
            "percent": 13.8
          },
          {
            "bucket": "<30s",
            "count": 27,
            "percent": 12.4
          },
          {
            "bucket": "30-60s",
            "count": 18,
            "percent": 8.3
          },
          {
            "bucket": "120-180s",
            "count": 11,
            "percent": 5.1
          },
          {
            "bucket": "180-300s",
            "count": 7,
            "percent": 3.2
          },
          {
            "bucket": "300s+",
            "count": 1,
            "percent": 0.5
          }
        ],
        "statusBreakdown": [
          {
            "status": "Unattended Dialled",
            "count": 114,
            "percent": 52.5
          },
          {
            "status": "Received",
            "count": 59,
            "percent": 27.2
          },
          {
            "status": "Attended Dialled",
            "count": 35,
            "percent": 16.1
          },
          {
            "status": "Missed",
            "count": 9,
            "percent": 4.1
          }
        ]
      },
      {
        "owner": "Neha Aziz",
        "totalCalls": 211,
        "connectedCalls": 117,
        "avgDurationSec": 116.8,
        "connectionRatePercent": 55.5,
        "avgBookingSeconds": 116.8,
        "peakHour": "20:00",
        "bucketBreakdown": [
          {
            "bucket": "0s",
            "count": 94,
            "percent": 44.5
          },
          {
            "bucket": "<30s",
            "count": 26,
            "percent": 12.3
          },
          {
            "bucket": "120-180s",
            "count": 25,
            "percent": 11.8
          },
          {
            "bucket": "30-60s",
            "count": 22,
            "percent": 10.4
          },
          {
            "bucket": "60-120s",
            "count": 20,
            "percent": 9.5
          },
          {
            "bucket": "180-300s",
            "count": 17,
            "percent": 8.1
          },
          {
            "bucket": "300s+",
            "count": 7,
            "percent": 3.3
          }
        ],
        "statusBreakdown": [
          {
            "status": "Unattended Dialled",
            "count": 91,
            "percent": 43.1
          },
          {
            "status": "Attended Dialled",
            "count": 79,
            "percent": 37.4
          },
          {
            "status": "Received",
            "count": 38,
            "percent": 18
          },
          {
            "status": "Missed",
            "count": 3,
            "percent": 1.4
          }
        ]
      },
      {
        "owner": "Reshma Reddy",
        "totalCalls": 195,
        "connectedCalls": 106,
        "avgDurationSec": 61.5,
        "connectionRatePercent": 54.4,
        "avgBookingSeconds": 61.5,
        "peakHour": "13:00",
        "bucketBreakdown": [
          {
            "bucket": "0s",
            "count": 89,
            "percent": 45.6
          },
          {
            "bucket": "<30s",
            "count": 41,
            "percent": 21
          },
          {
            "bucket": "60-120s",
            "count": 27,
            "percent": 13.8
          },
          {
            "bucket": "30-60s",
            "count": 21,
            "percent": 10.8
          },
          {
            "bucket": "120-180s",
            "count": 11,
            "percent": 5.6
          },
          {
            "bucket": "180-300s",
            "count": 6,
            "percent": 3.1
          }
        ],
        "statusBreakdown": [
          {
            "status": "Unattended Dialled",
            "count": 72,
            "percent": 36.9
          },
          {
            "status": "Attended Dialled",
            "count": 59,
            "percent": 30.3
          },
          {
            "status": "Received",
            "count": 47,
            "percent": 24.1
          },
          {
            "status": "Missed",
            "count": 17,
            "percent": 8.7
          }
        ]
      },
      {
        "owner": "Shahin BR",
        "totalCalls": 185,
        "connectedCalls": 112,
        "avgDurationSec": 85.1,
        "connectionRatePercent": 60.5,
        "avgBookingSeconds": 85.1,
        "peakHour": "16:00",
        "bucketBreakdown": [
          {
            "bucket": "0s",
            "count": 73,
            "percent": 39.5
          },
          {
            "bucket": "<30s",
            "count": 35,
            "percent": 18.9
          },
          {
            "bucket": "30-60s",
            "count": 28,
            "percent": 15.1
          },
          {
            "bucket": "120-180s",
            "count": 18,
            "percent": 9.7
          },
          {
            "bucket": "60-120s",
            "count": 16,
            "percent": 8.6
          },
          {
            "bucket": "180-300s",
            "count": 11,
            "percent": 5.9
          },
          {
            "bucket": "300s+",
            "count": 4,
            "percent": 2.2
          }
        ],
        "statusBreakdown": [
          {
            "status": "Unattended Dialled",
            "count": 73,
            "percent": 39.5
          },
          {
            "status": "Received",
            "count": 66,
            "percent": 35.7
          },
          {
            "status": "Attended Dialled",
            "count": 46,
            "percent": 24.9
          }
        ]
      },
      {
        "owner": "Rith Tamang",
        "totalCalls": 178,
        "connectedCalls": 121,
        "avgDurationSec": 97.1,
        "connectionRatePercent": 68,
        "avgBookingSeconds": 97.1,
        "peakHour": "08:00",
        "bucketBreakdown": [
          {
            "bucket": "0s",
            "count": 57,
            "percent": 32
          },
          {
            "bucket": "<30s",
            "count": 32,
            "percent": 18
          },
          {
            "bucket": "30-60s",
            "count": 26,
            "percent": 14.6
          },
          {
            "bucket": "60-120s",
            "count": 25,
            "percent": 14
          },
          {
            "bucket": "120-180s",
            "count": 17,
            "percent": 9.6
          },
          {
            "bucket": "180-300s",
            "count": 15,
            "percent": 8.4
          },
          {
            "bucket": "300s+",
            "count": 6,
            "percent": 3.4
          }
        ],
        "statusBreakdown": [
          {
            "status": "Received",
            "count": 75,
            "percent": 42.1
          },
          {
            "status": "Unattended Dialled",
            "count": 51,
            "percent": 28.7
          },
          {
            "status": "Attended Dialled",
            "count": 46,
            "percent": 25.8
          },
          {
            "status": "Missed",
            "count": 6,
            "percent": 3.4
          }
        ]
      },
      {
        "owner": "Rani KJ",
        "totalCalls": 125,
        "connectedCalls": 82,
        "avgDurationSec": 101.4,
        "connectionRatePercent": 65.6,
        "avgBookingSeconds": 101.4,
        "peakHour": "11:00",
        "bucketBreakdown": [
          {
            "bucket": "0s",
            "count": 43,
            "percent": 34.4
          },
          {
            "bucket": "<30s",
            "count": 26,
            "percent": 20.8
          },
          {
            "bucket": "30-60s",
            "count": 18,
            "percent": 14.4
          },
          {
            "bucket": "60-120s",
            "count": 11,
            "percent": 8.8
          },
          {
            "bucket": "180-300s",
            "count": 10,
            "percent": 8
          },
          {
            "bucket": "120-180s",
            "count": 10,
            "percent": 8
          },
          {
            "bucket": "300s+",
            "count": 7,
            "percent": 5.6
          }
        ],
        "statusBreakdown": [
          {
            "status": "Attended Dialled",
            "count": 45,
            "percent": 36
          },
          {
            "status": "Unattended Dialled",
            "count": 41,
            "percent": 32.8
          },
          {
            "status": "Received",
            "count": 37,
            "percent": 29.6
          },
          {
            "status": "Missed",
            "count": 2,
            "percent": 1.6
          }
        ]
      },
      {
        "owner": "Anuj Polladia",
        "totalCalls": 34,
        "connectedCalls": 18,
        "avgDurationSec": 86.9,
        "connectionRatePercent": 52.9,
        "avgBookingSeconds": 86.9,
        "peakHour": "10:00",
        "bucketBreakdown": [
          {
            "bucket": "0s",
            "count": 16,
            "percent": 47.1
          },
          {
            "bucket": "60-120s",
            "count": 8,
            "percent": 23.5
          },
          {
            "bucket": "30-60s",
            "count": 4,
            "percent": 11.8
          },
          {
            "bucket": "<30s",
            "count": 3,
            "percent": 8.8
          },
          {
            "bucket": "180-300s",
            "count": 2,
            "percent": 5.9
          },
          {
            "bucket": "120-180s",
            "count": 1,
            "percent": 2.9
          }
        ],
        "statusBreakdown": [
          {
            "status": "Received",
            "count": 16,
            "percent": 47.1
          },
          {
            "status": "Unattended Dialled",
            "count": 12,
            "percent": 35.3
          },
          {
            "status": "Missed",
            "count": 4,
            "percent": 11.8
          },
          {
            "status": "Attended Dialled",
            "count": 2,
            "percent": 5.9
          }
        ]
      },
      {
        "owner": "Himasri",
        "totalCalls": 30,
        "connectedCalls": 20,
        "avgDurationSec": 124.3,
        "connectionRatePercent": 66.7,
        "avgBookingSeconds": 124.3,
        "peakHour": "10:00",
        "bucketBreakdown": [
          {
            "bucket": "0s",
            "count": 10,
            "percent": 33.3
          },
          {
            "bucket": "120-180s",
            "count": 7,
            "percent": 23.3
          },
          {
            "bucket": "60-120s",
            "count": 5,
            "percent": 16.7
          },
          {
            "bucket": "<30s",
            "count": 4,
            "percent": 13.3
          },
          {
            "bucket": "180-300s",
            "count": 2,
            "percent": 6.7
          },
          {
            "bucket": "30-60s",
            "count": 1,
            "percent": 3.3
          },
          {
            "bucket": "300s+",
            "count": 1,
            "percent": 3.3
          }
        ],
        "statusBreakdown": [
          {
            "status": "Attended Dialled",
            "count": 13,
            "percent": 43.3
          },
          {
            "status": "Unattended Dialled",
            "count": 10,
            "percent": 33.3
          },
          {
            "status": "Received",
            "count": 7,
            "percent": 23.3
          }
        ]
      },
      {
        "owner": "Pardeep Kumar",
        "totalCalls": 25,
        "connectedCalls": 0,
        "avgDurationSec": 0,
        "connectionRatePercent": 0,
        "avgBookingSeconds": 0,
        "peakHour": "18:00",
        "bucketBreakdown": [
          {
            "bucket": "0s",
            "count": 25,
            "percent": 100
          }
        ],
        "statusBreakdown": [
          {
            "status": "Missed",
            "count": 25,
            "percent": 100
          }
        ]
      }
    ],
    "hourlyCounts": [
      0,
      0,
      0,
      0,
      0,
      0,
      0,
      3,
      64,
      91,
      128,
      162,
      131,
      117,
      86,
      98,
      98,
      51,
      36,
      44,
      82,
      7,
      1,
      1
    ]
  },
  "sampleSize": 1200
}