{
  "analysis": {
    "generatedAt": "2026-02-26T04:30:12.855Z",
    "totalCalls": 1200,
    "connectedCalls": 662,
    "avgDurationSec": 103.2,
    "medianDurationSec": 69,
    "bucketSummary": [
      {
        "bucket": "0s",
        "count": 538,
        "percent": 44.8
      },
      {
        "bucket": "<30s",
        "count": 172,
        "percent": 14.3
      },
      {
        "bucket": "60-120s",
        "count": 159,
        "percent": 13.3
      },
      {
        "bucket": "30-60s",
        "count": 137,
        "percent": 11.4
      },
      {
        "bucket": "180-300s",
        "count": 80,
        "percent": 6.7
      },
      {
        "bucket": "120-180s",
        "count": 76,
        "percent": 6.3
      },
      {
        "bucket": "300s+",
        "count": 38,
        "percent": 3.2
      }
    ],
    "statusSummary": [
      {
        "status": "Unattended Dialled",
        "count": 453,
        "percent": 37.8
      },
      {
        "status": "Attended Dialled",
        "count": 341,
        "percent": 28.4
      },
      {
        "status": "Received",
        "count": 321,
        "percent": 26.8
      },
      {
        "status": "Missed",
        "count": 85,
        "percent": 7.1
      }
    ],
    "typeSummary": [
      {
        "type": "Outbound",
        "count": 794,
        "percent": 66.2
      },
      {
        "type": "Inbound",
        "count": 321,
        "percent": 26.8
      },
      {
        "type": "Missed",
        "count": 85,
        "percent": 7.1
      }
    ],
    "totalTalkSeconds": 68314,
    "hourlyTalkSeconds": [
      0,
      0,
      0,
      0,
      0,
      0,
      0,
      0,
      5259,
      9678,
      4540,
      5258,
      6975,
      7394,
      5771,
      6134,
      3521,
      3928,
      3189,
      3507,
      3160,
      0,
      0,
      0
    ],
    "ownerSummary": [
      {
        "owner": "Neha Aziz",
        "totalCalls": 202,
        "connectedCalls": 113,
        "avgDurationSec": 111.5,
        "connectionRatePercent": 55.9,
        "avgBookingSeconds": 111.5,
        "peakHour": "20:00",
        "bucketBreakdown": [
          {
            "bucket": "0s",
            "count": 89,
            "percent": 44.1
          },
          {
            "bucket": "60-120s",
            "count": 27,
            "percent": 13.4
          },
          {
            "bucket": "<30s",
            "count": 25,
            "percent": 12.4
          },
          {
            "bucket": "30-60s",
            "count": 21,
            "percent": 10.4
          },
          {
            "bucket": "180-300s",
            "count": 20,
            "percent": 9.9
          },
          {
            "bucket": "120-180s",
            "count": 14,
            "percent": 6.9
          },
          {
            "bucket": "300s+",
            "count": 6,
            "percent": 3
          }
        ],
        "statusBreakdown": [
          {
            "status": "Unattended Dialled",
            "count": 87,
            "percent": 43.1
          },
          {
            "status": "Attended Dialled",
            "count": 70,
            "percent": 34.7
          },
          {
            "status": "Received",
            "count": 43,
            "percent": 21.3
          },
          {
            "status": "Missed",
            "count": 2,
            "percent": 1
          }
        ]
      },
      {
        "owner": "Rani KJ",
        "totalCalls": 187,
        "connectedCalls": 108,
        "avgDurationSec": 118.4,
        "connectionRatePercent": 57.8,
        "avgBookingSeconds": 118.4,
        "peakHour": "09:00",
        "bucketBreakdown": [
          {
            "bucket": "0s",
            "count": 79,
            "percent": 42.2
          },
          {
            "bucket": "30-60s",
            "count": 31,
            "percent": 16.6
          },
          {
            "bucket": "60-120s",
            "count": 24,
            "percent": 12.8
          },
          {
            "bucket": "180-300s",
            "count": 17,
            "percent": 9.1
          },
          {
            "bucket": "120-180s",
            "count": 15,
            "percent": 8
          },
          {
            "bucket": "<30s",
            "count": 15,
            "percent": 8
          },
          {
            "bucket": "300s+",
            "count": 6,
            "percent": 3.2
          }
        ],
        "statusBreakdown": [
          {
            "status": "Unattended Dialled",
            "count": 78,
            "percent": 41.7
          },
          {
            "status": "Attended Dialled",
            "count": 66,
            "percent": 35.3
          },
          {
            "status": "Received",
            "count": 42,
            "percent": 22.5
          },
          {
            "status": "Missed",
            "count": 1,
            "percent": 0.5
          }
        ]
      },
      {
        "owner": "Reshma Reddy",
        "totalCalls": 174,
        "connectedCalls": 89,
        "avgDurationSec": 80.1,
        "connectionRatePercent": 51.1,
        "avgBookingSeconds": 80.1,
        "peakHour": "18:00",
        "bucketBreakdown": [
          {
            "bucket": "0s",
            "count": 85,
            "percent": 48.9
          },
          {
            "bucket": "<30s",
            "count": 40,
            "percent": 23
          },
          {
            "bucket": "60-120s",
            "count": 17,
            "percent": 9.8
          },
          {
            "bucket": "30-60s",
            "count": 12,
            "percent": 6.9
          },
          {
            "bucket": "120-180s",
            "count": 8,
            "percent": 4.6
          },
          {
            "bucket": "180-300s",
            "count": 7,
            "percent": 4
          },
          {
            "bucket": "300s+",
            "count": 5,
            "percent": 2.9
          }
        ],
        "statusBreakdown": [
          {
            "status": "Unattended Dialled",
            "count": 74,
            "percent": 42.5
          },
          {
            "status": "Attended Dialled",
            "count": 56,
            "percent": 32.2
          },
          {
            "status": "Received",
            "count": 33,
            "percent": 19
          },
          {
            "status": "Missed",
            "count": 11,
            "percent": 6.3
          }
        ]
      },
      {
        "owner": "Shahin BR",
        "totalCalls": 166,
        "connectedCalls": 103,
        "avgDurationSec": 82,
        "connectionRatePercent": 62,
        "avgBookingSeconds": 82,
        "peakHour": "14:00",
        "bucketBreakdown": [
          {
            "bucket": "0s",
            "count": 63,
            "percent": 38
          },
          {
            "bucket": "<30s",
            "count": 35,
            "percent": 21.1
          },
          {
            "bucket": "60-120s",
            "count": 25,
            "percent": 15.1
          },
          {
            "bucket": "30-60s",
            "count": 21,
            "percent": 12.7
          },
          {
            "bucket": "180-300s",
            "count": 9,
            "percent": 5.4
          },
          {
            "bucket": "120-180s",
            "count": 9,
            "percent": 5.4
          },
          {
            "bucket": "300s+",
            "count": 4,
            "percent": 2.4
          }
        ],
        "statusBreakdown": [
          {
            "status": "Unattended Dialled",
            "count": 62,
            "percent": 37.3
          },
          {
            "status": "Received",
            "count": 59,
            "percent": 35.5
          },
          {
            "status": "Attended Dialled",
            "count": 44,
            "percent": 26.5
          },
          {
            "status": "Missed",
            "count": 1,
            "percent": 0.6
          }
        ]
      },
      {
        "owner": "Himasri",
        "totalCalls": 137,
        "connectedCalls": 83,
        "avgDurationSec": 135.3,
        "connectionRatePercent": 60.6,
        "avgBookingSeconds": 135.3,
        "peakHour": "09:00",
        "bucketBreakdown": [
          {
            "bucket": "0s",
            "count": 54,
            "percent": 39.4
          },
          {
            "bucket": "60-120s",
            "count": 21,
            "percent": 15.3
          },
          {
            "bucket": "<30s",
            "count": 21,
            "percent": 15.3
          },
          {
            "bucket": "30-60s",
            "count": 13,
            "percent": 9.5
          },
          {
            "bucket": "300s+",
            "count": 11,
            "percent": 8
          },
          {
            "bucket": "180-300s",
            "count": 11,
            "percent": 8
          },
          {
            "bucket": "120-180s",
            "count": 6,
            "percent": 4.4
          }
        ],
        "statusBreakdown": [
          {
            "status": "Received",
            "count": 48,
            "percent": 35
          },
          {
            "status": "Unattended Dialled",
            "count": 46,
            "percent": 33.6
          },
          {
            "status": "Attended Dialled",
            "count": 35,
            "percent": 25.5
          },
          {
            "status": "Missed",
            "count": 8,
            "percent": 5.8
          }
        ]
      },
      {
        "owner": "Rajeswari R",
        "totalCalls": 112,
        "connectedCalls": 58,
        "avgDurationSec": 77.2,
        "connectionRatePercent": 51.8,
        "avgBookingSeconds": 77.2,
        "peakHour": "09:00",
        "bucketBreakdown": [
          {
            "bucket": "0s",
            "count": 54,
            "percent": 48.2
          },
          {
            "bucket": "30-60s",
            "count": 17,
            "percent": 15.2
          },
          {
            "bucket": "<30s",
            "count": 15,
            "percent": 13.4
          },
          {
            "bucket": "60-120s",
            "count": 13,
            "percent": 11.6
          },
          {
            "bucket": "120-180s",
            "count": 8,
            "percent": 7.1
          },
          {
            "bucket": "180-300s",
            "count": 5,
            "percent": 4.5
          }
        ],
        "statusBreakdown": [
          {
            "status": "Unattended Dialled",
            "count": 51,
            "percent": 45.5
          },
          {
            "status": "Attended Dialled",
            "count": 33,
            "percent": 29.5
          },
          {
            "status": "Received",
            "count": 25,
            "percent": 22.3
          },
          {
            "status": "Missed",
            "count": 3,
            "percent": 2.7
          }
        ]
      },
      {
        "owner": "Anuj Polladia",
        "totalCalls": 103,
        "connectedCalls": 60,
        "avgDurationSec": 130.8,
        "connectionRatePercent": 58.3,
        "avgBookingSeconds": 130.8,
        "peakHour": "19:00",
        "bucketBreakdown": [
          {
            "bucket": "0s",
            "count": 43,
            "percent": 41.7
          },
          {
            "bucket": "60-120s",
            "count": 18,
            "percent": 17.5
          },
          {
            "bucket": "30-60s",
            "count": 14,
            "percent": 13.6
          },
          {
            "bucket": "180-300s",
            "count": 9,
            "percent": 8.7
          },
          {
            "bucket": "120-180s",
            "count": 8,
            "percent": 7.8
          },
          {
            "bucket": "<30s",
            "count": 6,
            "percent": 5.8
          },
          {
            "bucket": "300s+",
            "count": 5,
            "percent": 4.9
          }
        ],
        "statusBreakdown": [
          {
            "status": "Received",
            "count": 46,
            "percent": 44.7
          },
          {
            "status": "Unattended Dialled",
            "count": 32,
            "percent": 31.1
          },
          {
            "status": "Attended Dialled",
            "count": 14,
            "percent": 13.6
          },
          {
            "status": "Missed",
            "count": 11,
            "percent": 10.7
          }
        ]
      },
      {
        "owner": "Rith Tamang",
        "totalCalls": 73,
        "connectedCalls": 48,
        "avgDurationSec": 79.3,
        "connectionRatePercent": 65.8,
        "avgBookingSeconds": 79.3,
        "peakHour": "09:00",
        "bucketBreakdown": [
          {
            "bucket": "0s",
            "count": 25,
            "percent": 34.2
          },
          {
            "bucket": "<30s",
            "count": 15,
            "percent": 20.5
          },
          {
            "bucket": "60-120s",
            "count": 14,
            "percent": 19.2
          },
          {
            "bucket": "30-60s",
            "count": 8,
            "percent": 11
          },
          {
            "bucket": "120-180s",
            "count": 8,
            "percent": 11
          },
          {
            "bucket": "180-300s",
            "count": 2,
            "percent": 2.7
          },
          {
            "bucket": "300s+",
            "count": 1,
            "percent": 1.4
          }
        ],
        "statusBreakdown": [
          {
            "status": "Received",
            "count": 25,
            "percent": 34.2
          },
          {
            "status": "Attended Dialled",
            "count": 23,
            "percent": 31.5
          },
          {
            "status": "Unattended Dialled",
            "count": 23,
            "percent": 31.5
          },
          {
            "status": "Missed",
            "count": 2,
            "percent": 2.7
          }
        ]
      },
      {
        "owner": "Pardeep Kumar",
        "totalCalls": 46,
        "connectedCalls": 0,
        "avgDurationSec": 0,
        "connectionRatePercent": 0,
        "avgBookingSeconds": 0,
        "peakHour": "21:00",
        "bucketBreakdown": [
          {
            "bucket": "0s",
            "count": 46,
            "percent": 100
          }
        ],
        "statusBreakdown": [
          {
            "status": "Missed",
            "count": 46,
            "percent": 100
          }
        ]
      }
    ],
    "hourlyCounts": [
      0,
      0,
      0,
      0,
      0,
      0,
      0,
      6,
      74,
      179,
      83,
      77,
      126,
      118,
      99,
      84,
      82,
      66,
      63,
      69,
      57,
      14,
      3,
      0
    ]
  },
  "sampleSize": 1200
}