[
  {
    "agent": "Rani KJ",
    "topConversion": {
      "bucket": "60-120s",
      "rate": 0,
      "count": 0
    },
    "topRejection": {
      "bucket": "<60s",
      "rate": 1,
      "count": 6
    },
    "sweetSpot": {
      "bucket": "60-120s",
      "score": -0.5,
      "conversionRate": 0,
      "rejectionRate": 0.5
    },
    "bucketDetails": [
      {
        "bucket": "60-120s",
        "phones": 2,
        "converted": 0,
        "rejected": 1,
        "conversionRate": 0,
        "rejectionRate": 0.5
      },
      {
        "bucket": "<60s",
        "phones": 6,
        "converted": 0,
        "rejected": 6,
        "conversionRate": 0,
        "rejectionRate": 1
      },
      {
        "bucket": "180-300s",
        "phones": 1,
        "converted": 0,
        "rejected": 1,
        "conversionRate": 0,
        "rejectionRate": 1
      }
    ]
  },
  {
    "agent": "Himasri",
    "topConversion": {
      "bucket": "<60s",
      "rate": 0.14285714285714285,
      "count": 1
    },
    "topRejection": {
      "bucket": "<60s",
      "rate": 0.5714285714285714,
      "count": 4
    },
    "sweetSpot": {
      "bucket": "<60s",
      "score": -0.42857142857142855,
      "conversionRate": 0.14285714285714285,
      "rejectionRate": 0.5714285714285714
    },
    "bucketDetails": [
      {
        "bucket": "<60s",
        "phones": 7,
        "converted": 1,
        "rejected": 4,
        "conversionRate": 0.14285714285714285,
        "rejectionRate": 0.5714285714285714
      },
      {
        "bucket": "60-120s",
        "phones": 4,
        "converted": 0,
        "rejected": 2,
        "conversionRate": 0,
        "rejectionRate": 0.5
      }
    ]
  },
  {
    "agent": "Shahin BR",
    "topConversion": {
      "bucket": "<60s",
      "rate": 0,
      "count": 0
    },
    "topRejection": {
      "bucket": "60-120s",
      "rate": 1,
      "count": 1
    },
    "sweetSpot": {
      "bucket": "<60s",
      "score": -0.5,
      "conversionRate": 0,
      "rejectionRate": 0.5
    },
    "bucketDetails": [
      {
        "bucket": "<60s",
        "phones": 6,
        "converted": 0,
        "rejected": 3,
        "conversionRate": 0,
        "rejectionRate": 0.5
      },
      {
        "bucket": "60-120s",
        "phones": 1,
        "converted": 0,
        "rejected": 1,
        "conversionRate": 0,
        "rejectionRate": 1
      }
    ]
  },
  {
    "agent": "Rith Tamang",
    "topConversion": {
      "bucket": "<60s",
      "rate": 0,
      "count": 0
    },
    "topRejection": {
      "bucket": "120-180s",
      "rate": 1,
      "count": 1
    },
    "sweetSpot": {
      "bucket": "<60s",
      "score": -0.6666666666666666,
      "conversionRate": 0,
      "rejectionRate": 0.6666666666666666
    },
    "bucketDetails": [
      {
        "bucket": "<60s",
        "phones": 6,
        "converted": 0,
        "rejected": 4,
        "conversionRate": 0,
        "rejectionRate": 0.6666666666666666
      },
      {
        "bucket": "120-180s",
        "phones": 1,
        "converted": 0,
        "rejected": 1,
        "conversionRate": 0,
        "rejectionRate": 1
      },
      {
        "bucket": "60-120s",
        "phones": 3,
        "converted": 0,
        "rejected": 3,
        "conversionRate": 0,
        "rejectionRate": 1
      }
    ]
  },
  {
    "agent": "Reshma Reddy",
    "topConversion": {
      "bucket": "<60s",
      "rate": 0.18181818181818182,
      "count": 2
    },
    "topRejection": {
      "bucket": "60-120s",
      "rate": 1,
      "count": 1
    },
    "sweetSpot": {
      "bucket": "<60s",
      "score": -0.5454545454545454,
      "conversionRate": 0.18181818181818182,
      "rejectionRate": 0.7272727272727273
    },
    "bucketDetails": [
      {
        "bucket": "<60s",
        "phones": 11,
        "converted": 2,
        "rejected": 8,
        "conversionRate": 0.18181818181818182,
        "rejectionRate": 0.7272727272727273
      },
      {
        "bucket": "60-120s",
        "phones": 1,
        "converted": 0,
        "rejected": 1,
        "conversionRate": 0,
        "rejectionRate": 1
      },
      {
        "bucket": "180-300s",
        "phones": 2,
        "converted": 0,
        "rejected": 2,
        "conversionRate": 0,
        "rejectionRate": 1
      }
    ]
  },
  {
    "agent": "Neha Aziz",
    "topConversion": {
      "bucket": "120-180s",
      "rate": 0.3333333333333333,
      "count": 1
    },
    "topRejection": {
      "bucket": "180-300s",
      "rate": 1,
      "count": 2
    },
    "sweetSpot": {
      "bucket": "120-180s",
      "score": -0.3333333333333333,
      "conversionRate": 0.3333333333333333,
      "rejectionRate": 0.6666666666666666
    },
    "bucketDetails": [
      {
        "bucket": "120-180s",
        "phones": 3,
        "converted": 1,
        "rejected": 2,
        "conversionRate": 0.3333333333333333,
        "rejectionRate": 0.6666666666666666
      },
      {
        "bucket": "<60s",
        "phones": 5,
        "converted": 0,
        "rejected": 2,
        "conversionRate": 0,
        "rejectionRate": 0.4
      },
      {
        "bucket": "180-300s",
        "phones": 2,
        "converted": 0,
        "rejected": 2,
        "conversionRate": 0,
        "rejectionRate": 1
      },
      {
        "bucket": "60-120s",
        "phones": 3,
        "converted": 0,
        "rejected": 3,
        "conversionRate": 0,
        "rejectionRate": 1
      }
    ]
  },
  {
    "agent": "Anuj Polladia",
    "topConversion": {
      "bucket": "180-300s",
      "rate": 0,
      "count": 0
    },
    "topRejection": {
      "bucket": "180-300s",
      "rate": 1,
      "count": 1
    },
    "sweetSpot": {
      "bucket": "180-300s",
      "score": -1,
      "conversionRate": 0,
      "rejectionRate": 1
    },
    "bucketDetails": [
      {
        "bucket": "180-300s",
        "phones": 1,
        "converted": 0,
        "rejected": 1,
        "conversionRate": 0,
        "rejectionRate": 1
      },
      {
        "bucket": "60-120s",
        "phones": 1,
        "converted": 0,
        "rejected": 1,
        "conversionRate": 0,
        "rejectionRate": 1
      }
    ]
  }
]