{
  "generatedAt": "2026-02-24T09:07:02.445Z",
  "kpis": {
    "todaysLeadsCount": 87,
    "nc1Count": 53,
    "nc2Count": 35,
    "nc3Count": 7,
    "leadToDealConversionPercent": 33.1,
    "totalDealsCount": 43,
    "totalTasksCount": 76,
    "taskCompletionPercent": 17.1,
    "retentionRate": 75,
    "avgCallDurationSec": 77,
    "followupComplianceRate": 91.5
  },
  "retention": {
    "labels": [
      "00:00",
      "01:00",
      "02:00",
      "03:00",
      "04:00",
      "05:00",
      "06:00",
      "07:00",
      "08:00",
      "09:00",
      "10:00",
      "11:00",
      "12:00",
      "13:00",
      "14:00"
    ],
    "values": [
      100,
      0,
      100,
      50,
      0,
      100,
      100,
      66.7,
      100,
      77.8,
      100,
      83.3,
      94.7,
      92.3,
      75
    ]
  },
  "calls": {
    "labels": [
      "Mon",
      "Tue",
      "Wed",
      "Thu",
      "Fri",
      "Sat",
      "Sun"
    ],
    "avgDurationSec": [
      0,
      44,
      0,
      0,
      0,
      0,
      0
    ],
    "callCounts": [
      2,
      198,
      0,
      0,
      0,
      0,
      0
    ]
  },
  "compliance": {
    "called": 183,
    "notCalled": 17,
    "modifiedWithoutCall": 17
  },
  "ncTime": {
    "lookbackDays": 7,
    "idealHour": "12:00",
    "idealScore": 0.389,
    "peakNC1Hour": "09:00",
    "peakNC1Count": 14,
    "peakNC2Hour": "16:00",
    "peakNC2Count": 20,
    "labels": [
      "00:00",
      "01:00",
      "02:00",
      "03:00",
      "04:00",
      "05:00",
      "06:00",
      "07:00",
      "08:00",
      "09:00",
      "10:00",
      "11:00",
      "12:00",
      "13:00",
      "14:00",
      "15:00",
      "16:00",
      "17:00",
      "18:00",
      "19:00",
      "20:00",
      "21:00",
      "22:00",
      "23:00"
    ],
    "nc1": [
      0,
      0,
      0,
      0,
      0,
      0,
      0,
      0,
      4,
      14,
      5,
      1,
      10,
      4,
      4,
      1,
      1,
      4,
      1,
      0,
      4,
      0,
      0,
      0
    ],
    "nc2": [
      0,
      0,
      0,
      0,
      0,
      0,
      0,
      0,
      0,
      2,
      0,
      0,
      0,
      1,
      1,
      1,
      20,
      0,
      0,
      2,
      8,
      0,
      0,
      0
    ]
  },
  "ncLadder": {
    "lookbackDays": 7,
    "funnel": {
      "nc1": 95,
      "nc2": 42,
      "nc3": 7
    },
    "directFunnel": {
      "nc1": 53,
      "nc2": 35,
      "nc3": 7
    },
    "progression": {
      "nc1ToNc2Percent": 66,
      "nc2ToNc3Percent": 20,
      "avgHoursNc1ToNc2": 31.6,
      "avgHoursNc2ToNc3": 55.9
    },
    "sla": {
      "nc1ToNc2Hours": 4,
      "nc2ToNc3Hours": 24,
      "overdueNc1": 25,
      "overdueNc2": 20
    },
    "idealByStage": {
      "nc1": {
        "hour": "09:00",
        "count": 14,
        "score": 0.138
      },
      "nc2": {
        "hour": "16:00",
        "count": 20,
        "score": 0
      },
      "nc3": {
        "hour": "20:00",
        "count": 3,
        "score": 0.003
      }
    }
  },
  "latestLeadsToday": [
    {
      "name": "Incoming Call Lead",
      "phone": "8073168875",
      "owner": "Shahin BR",
      "leadStatus": "Open Leads",
      "leadSubStatus": "--",
      "createdTime": "2026-02-24T14:36:34+05:30",
      "called": true,
      "modifiedTime": "2026-02-24T14:36:35+05:30"
    },
    {
      "name": "Incoming Call Lead",
      "phone": "6304701479",
      "owner": "Rani KJ",
      "leadStatus": "Rejected",
      "leadSubStatus": "Service Not Available",
      "createdTime": "2026-02-24T14:34:41+05:30",
      "called": true,
      "modifiedTime": "2026-02-24T14:36:40+05:30"
    },
    {
      "name": "Sushmita",
      "phone": "9798607818",
      "owner": "Rani KJ",
      "leadStatus": "Open Leads",
      "leadSubStatus": "Not Contacted",
      "createdTime": "2026-02-24T14:24:56+05:30",
      "called": false,
      "modifiedTime": "2026-02-24T14:24:56+05:30"
    },
    {
      "name": "Design Concepts",
      "phone": "+919008290012",
      "owner": "Pardeep Kumar",
      "leadStatus": "Open Leads",
      "leadSubStatus": "Not Contacted",
      "createdTime": "2026-02-24T14:11:04+05:30",
      "called": true,
      "modifiedTime": "2026-02-24T14:13:54+05:30"
    },
    {
      "name": "Govind S",
      "phone": "09538954659",
      "owner": "Reshma Reddy",
      "leadStatus": "Attempted Contact",
      "leadSubStatus": "NC 1",
      "createdTime": "2026-02-24T13:58:26+05:30",
      "called": true,
      "modifiedTime": "2026-02-24T14:20:52+05:30"
    },
    {
      "name": "Nagendra Krishnamurthy",
      "phone": "9880214875",
      "owner": "Rith Tamang",
      "leadStatus": "Open Leads",
      "leadSubStatus": "Not Contacted",
      "createdTime": "2026-02-24T13:57:26+05:30",
      "called": true,
      "modifiedTime": "2026-02-24T14:19:35+05:30"
    },
    {
      "name": "Incoming Call Lead",
      "phone": "9886298462",
      "owner": "Amala",
      "leadStatus": "Open Leads",
      "leadSubStatus": "--",
      "createdTime": "2026-02-24T13:56:45+05:30",
      "called": true,
      "modifiedTime": "2026-02-24T14:08:22+05:30"
    },
    {
      "name": "Incoming Call Lead",
      "phone": "8970735521",
      "owner": "Neha Aziz",
      "leadStatus": "Open Leads",
      "leadSubStatus": "--",
      "createdTime": "2026-02-24T13:55:12+05:30",
      "called": true,
      "modifiedTime": "2026-02-24T14:00:20+05:30"
    },
    {
      "name": "Avinash",
      "phone": "9718316367",
      "owner": "Rani KJ",
      "leadStatus": "Rejected",
      "leadSubStatus": "Just Enquiring",
      "createdTime": "2026-02-24T13:38:56+05:30",
      "called": true,
      "modifiedTime": "2026-02-24T13:41:03+05:30"
    },
    {
      "name": "Sangamesh Narayanan",
      "phone": "9871541393",
      "owner": "Rith Tamang",
      "leadStatus": "Open Leads",
      "leadSubStatus": "Not Contacted",
      "createdTime": "2026-02-24T13:36:26+05:30",
      "called": true,
      "modifiedTime": "2026-02-24T14:00:20+05:30"
    },
    {
      "name": "Kamal",
      "phone": "9620213031",
      "owner": "Rith Tamang",
      "leadStatus": "Rejected",
      "leadSubStatus": "Duplicate",
      "createdTime": "2026-02-24T13:26:56+05:30",
      "called": true,
      "modifiedTime": "2026-02-24T13:47:47+05:30"
    },
    {
      "name": "Ullas",
      "phone": "7892587433",
      "owner": "Pardeep Kumar",
      "leadStatus": "Open Leads",
      "leadSubStatus": "Not Contacted",
      "createdTime": "2026-02-24T13:15:26+05:30",
      "called": false,
      "modifiedTime": "2026-02-24T13:15:26+05:30"
    },
    {
      "name": "Incoming Call Lead",
      "phone": "8970077085",
      "owner": "Neha Aziz",
      "leadStatus": "Rejected",
      "leadSubStatus": "Duplicate",
      "createdTime": "2026-02-24T13:12:42+05:30",
      "called": true,
      "modifiedTime": "2026-02-24T13:59:04+05:30"
    },
    {
      "name": "Incoming Call Lead",
      "phone": "7208450158",
      "owner": "Shahin BR",
      "leadStatus": "Rejected",
      "leadSubStatus": "Service Not Available",
      "createdTime": "2026-02-24T13:11:56+05:30",
      "called": true,
      "modifiedTime": "2026-02-24T13:14:24+05:30"
    },
    {
      "name": "Incoming Call Lead",
      "phone": "9632246715",
      "owner": "Himasri",
      "leadStatus": "Rejected",
      "leadSubStatus": "Slot Not Available",
      "createdTime": "2026-02-24T13:07:17+05:30",
      "called": true,
      "modifiedTime": "2026-02-24T13:21:25+05:30"
    },
    {
      "name": "Incoming Call Lead",
      "phone": "9743717576",
      "owner": "Neha Aziz",
      "leadStatus": "Rejected",
      "leadSubStatus": "Just Enquiring",
      "createdTime": "2026-02-24T13:04:42+05:30",
      "called": true,
      "modifiedTime": "2026-02-24T13:57:17+05:30"
    },
    {
      "name": "Ramappa Kumsher Basavarajappa",
      "phone": "7829862766",
      "owner": "Neha Aziz",
      "leadStatus": "Attempted Contact",
      "leadSubStatus": "NC 1",
      "createdTime": "2026-02-24T13:02:26+05:30",
      "called": true,
      "modifiedTime": "2026-02-24T13:55:59+05:30"
    },
    {
      "name": "Incoming Call Lead",
      "phone": "8840228927",
      "owner": "Himasri",
      "leadStatus": "Open Leads",
      "leadSubStatus": "--",
      "createdTime": "2026-02-24T12:59:42+05:30",
      "called": true,
      "modifiedTime": "2026-02-24T14:00:24+05:30"
    },
    {
      "name": "sasi kumar",
      "phone": "9886629261",
      "owner": "Reshma Reddy",
      "leadStatus": "Rejected",
      "leadSubStatus": "Price is high",
      "createdTime": "2026-02-24T12:59:11+05:30",
      "called": true,
      "modifiedTime": "2026-02-24T13:17:27+05:30"
    },
    {
      "name": "Incoming Call Lead",
      "phone": "7259115366",
      "owner": "Anuj Polladia",
      "leadStatus": "Contacted",
      "leadSubStatus": "Call Back Later",
      "createdTime": "2026-02-24T12:49:17+05:30",
      "called": true,
      "modifiedTime": "2026-02-24T13:06:57+05:30"
    },
    {
      "name": "Incoming Call Lead",
      "phone": "6361205836",
      "owner": "Shahin BR",
      "leadStatus": "Rejected",
      "leadSubStatus": "Just Enquiring",
      "createdTime": "2026-02-24T12:46:57+05:30",
      "called": true,
      "modifiedTime": "2026-02-24T12:48:01+05:30"
    },
    {
      "name": "Incoming Call Lead",
      "phone": "9902909507",
      "owner": "Rith Tamang",
      "leadStatus": "Rejected",
      "leadSubStatus": "Just Enquiring",
      "createdTime": "2026-02-24T12:44:34+05:30",
      "called": true,
      "modifiedTime": "2026-02-24T13:13:41+05:30"
    },
    {
      "name": "Incoming Call Lead",
      "phone": "9535293845",
      "owner": "Rith Tamang",
      "leadStatus": "Open Leads",
      "leadSubStatus": "--",
      "createdTime": "2026-02-24T12:40:39+05:30",
      "called": true,
      "modifiedTime": "2026-02-24T14:00:24+05:30"
    },
    {
      "name": "Incoming Call Lead",
      "phone": "7448880861",
      "owner": "Rith Tamang",
      "leadStatus": "Rejected",
      "leadSubStatus": "Just Enquiring",
      "createdTime": "2026-02-24T12:40:00+05:30",
      "called": true,
      "modifiedTime": "2026-02-24T12:40:21+05:30"
    },
    {
      "name": "Incoming Call Lead",
      "phone": "9952743633",
      "owner": "Rith Tamang",
      "leadStatus": "Rejected",
      "leadSubStatus": "Just Enquiring",
      "createdTime": "2026-02-24T12:33:49+05:30",
      "called": true,
      "modifiedTime": "2026-02-24T12:34:19+05:30"
    },
    {
      "name": "sanjay",
      "phone": "9606524031",
      "owner": "Reshma Reddy",
      "leadStatus": "Rejected",
      "leadSubStatus": "Just Enquiring",
      "createdTime": "2026-02-24T12:33:41+05:30",
      "called": true,
      "modifiedTime": "2026-02-24T12:53:50+05:30"
    },
    {
      "name": "Incoming Call Lead",
      "phone": "9731590977",
      "owner": "Shahin BR",
      "leadStatus": "Rejected",
      "leadSubStatus": "Just Enquiring",
      "createdTime": "2026-02-24T12:31:48+05:30",
      "called": true,
      "modifiedTime": "2026-02-24T12:32:35+05:30"
    },
    {
      "name": "Incoming Call Lead",
      "phone": "8904598110",
      "owner": "Rith Tamang",
      "leadStatus": "Rejected",
      "leadSubStatus": "Just Enquiring",
      "createdTime": "2026-02-24T12:31:22+05:30",
      "called": true,
      "modifiedTime": "2026-02-24T12:32:53+05:30"
    },
    {
      "name": "Sanjay",
      "phone": "+918749055950",
      "owner": "Vineeth Wankhade",
      "leadStatus": "Open Leads",
      "leadSubStatus": "Not Contacted",
      "createdTime": "2026-02-24T12:28:36+05:30",
      "called": true,
      "modifiedTime": "2026-02-24T12:36:43+05:30"
    },
    {
      "name": "Incoming Call Lead",
      "phone": "9398551696",
      "owner": "Shahin BR",
      "leadStatus": "Rejected",
      "leadSubStatus": "Service Not Available",
      "createdTime": "2026-02-24T12:26:36+05:30",
      "called": true,
      "modifiedTime": "2026-02-24T12:28:41+05:30"
    },
    {
      "name": "Kiran",
      "phone": "9901444498",
      "owner": "Shahin BR",
      "leadStatus": "Open Leads",
      "leadSubStatus": "Not Contacted",
      "createdTime": "2026-02-24T12:20:55+05:30",
      "called": true,
      "modifiedTime": "2026-02-24T14:00:24+05:30"
    },
    {
      "name": "Incoming Call Lead",
      "phone": "9986016380",
      "owner": "Neha Aziz",
      "leadStatus": "Open Leads",
      "leadSubStatus": "--",
      "createdTime": "2026-02-24T12:15:21+05:30",
      "called": true,
      "modifiedTime": "2026-02-24T14:00:23+05:30"
    },
    {
      "name": "Incoming Call Lead",
      "phone": "9999779857",
      "owner": "Shahin BR",
      "leadStatus": "Rejected",
      "leadSubStatus": "Price is high",
      "createdTime": "2026-02-24T12:11:00+05:30",
      "called": true,
      "modifiedTime": "2026-02-24T12:11:51+05:30"
    },
    {
      "name": "Incoming Call Lead",
      "phone": "9900057502",
      "owner": "Anuj Polladia",
      "leadStatus": "Rejected",
      "leadSubStatus": "Just Enquiring",
      "createdTime": "2026-02-24T12:10:28+05:30",
      "called": true,
      "modifiedTime": "2026-02-24T12:13:39+05:30"
    },
    {
      "name": "Anish V",
      "phone": "9535038379",
      "owner": "Reshma Reddy",
      "leadStatus": "Open Leads",
      "leadSubStatus": "Not Contacted",
      "createdTime": "2026-02-24T12:03:25+05:30",
      "called": false,
      "modifiedTime": "2026-02-24T12:03:25+05:30"
    },
    {
      "name": "Sandeep",
      "phone": "9731537971",
      "owner": "Neha Aziz",
      "leadStatus": "Attempted Contact",
      "leadSubStatus": "NC 1",
      "createdTime": "2026-02-24T12:02:55+05:30",
      "called": true,
      "modifiedTime": "2026-02-24T12:58:49+05:30"
    },
    {
      "name": "Architha K P",
      "phone": "8217397896",
      "owner": "Himasri",
      "leadStatus": "Open Leads",
      "leadSubStatus": "Not Contacted",
      "createdTime": "2026-02-24T11:59:55+05:30",
      "called": false,
      "modifiedTime": "2026-02-24T11:59:55+05:30"
    },
    {
      "name": "HARISH Dasappa",
      "phone": "08762093372",
      "owner": "Rani KJ",
      "leadStatus": "Open Leads",
      "leadSubStatus": "Not Contacted",
      "createdTime": "2026-02-24T11:57:55+05:30",
      "called": false,
      "modifiedTime": "2026-02-24T11:57:55+05:30"
    },
    {
      "name": "Incoming Call Lead",
      "phone": "8447749126",
      "owner": "Rani KJ",
      "leadStatus": "Rejected",
      "leadSubStatus": "Out Of Service Area",
      "createdTime": "2026-02-24T11:54:58+05:30",
      "called": true,
      "modifiedTime": "2026-02-24T11:55:36+05:30"
    },
    {
      "name": "Sanjeev",
      "phone": "9845616646",
      "owner": "Reshma Reddy",
      "leadStatus": "Attempted Contact",
      "leadSubStatus": "NC 1",
      "createdTime": "2026-02-24T11:52:54+05:30",
      "called": true,
      "modifiedTime": "2026-02-24T12:06:54+05:30"
    },
    {
      "name": "Incoming Call Lead",
      "phone": "9844930050",
      "owner": "Himasri",
      "leadStatus": "Open Leads",
      "leadSubStatus": "--",
      "createdTime": "2026-02-24T11:52:24+05:30",
      "called": true,
      "modifiedTime": "2026-02-24T14:00:21+05:30"
    },
    {
      "name": "Incoming Call Lead",
      "phone": "9606775463",
      "owner": "Himasri",
      "leadStatus": "Rejected",
      "leadSubStatus": "Just Enquiring",
      "createdTime": "2026-02-24T11:51:36+05:30",
      "called": true,
      "modifiedTime": "2026-02-24T11:54:44+05:30"
    },
    {
      "name": "Incoming Call Lead",
      "phone": "9606775463",
      "owner": "Himasri",
      "leadStatus": "Rejected",
      "leadSubStatus": "Just Enquiring",
      "createdTime": "2026-02-24T11:51:36+05:30",
      "called": true,
      "modifiedTime": "2026-02-24T11:55:38+05:30"
    },
    {
      "name": "Incoming Call Lead",
      "phone": "9050217554",
      "owner": "Shahin BR",
      "leadStatus": "Contacted",
      "leadSubStatus": "Call Back Later",
      "createdTime": "2026-02-24T11:49:52+05:30",
      "called": true,
      "modifiedTime": "2026-02-24T12:10:27+05:30"
    },
    {
      "name": "Sabiha",
      "phone": "9845244323",
      "owner": "Rith Tamang",
      "leadStatus": "Attempted Contact",
      "leadSubStatus": "NC 1",
      "createdTime": "2026-02-24T11:39:54+05:30",
      "called": true,
      "modifiedTime": "2026-02-24T12:08:34+05:30"
    },
    {
      "name": "Incoming Call Lead",
      "phone": "9819572577",
      "owner": "Himasri",
      "leadStatus": "Rejected",
      "leadSubStatus": "Just Enquiring",
      "createdTime": "2026-02-24T11:30:51+05:30",
      "called": true,
      "modifiedTime": "2026-02-24T11:51:55+05:30"
    },
    {
      "name": "Debasis Sahoo",
      "phone": "9836548181",
      "owner": "Anuj Polladia",
      "leadStatus": "Open Leads",
      "leadSubStatus": "Not Contacted",
      "createdTime": "2026-02-24T11:16:54+05:30",
      "called": true,
      "modifiedTime": "2026-02-24T14:00:22+05:30"
    },
    {
      "name": "Incoming Call Lead",
      "phone": "9901302226",
      "owner": "Anuj Polladia",
      "leadStatus": "Rejected",
      "leadSubStatus": "Just Enquiring",
      "createdTime": "2026-02-24T11:06:32+05:30",
      "called": true,
      "modifiedTime": "2026-02-24T11:32:58+05:30"
    },
    {
      "name": "Incoming Call Lead",
      "phone": "9739981745",
      "owner": "Rani KJ",
      "leadStatus": "Rejected",
      "leadSubStatus": "Service Not Available",
      "createdTime": "2026-02-24T10:49:11+05:30",
      "called": true,
      "modifiedTime": "2026-02-24T10:51:47+05:30"
    },
    {
      "name": "Incoming Call Lead",
      "phone": "9902352071",
      "owner": "Neha Aziz",
      "leadStatus": "Contacted",
      "leadSubStatus": "Call Back Later",
      "createdTime": "2026-02-24T10:46:50+05:30",
      "called": true,
      "modifiedTime": "2026-02-24T11:04:47+05:30"
    },
    {
      "name": "Nandakumar",
      "phone": "9901435333",
      "owner": "Amala",
      "leadStatus": "Rejected",
      "leadSubStatus": "Just Enquiring",
      "createdTime": "2026-02-24T10:44:53+05:30",
      "called": true,
      "modifiedTime": "2026-02-24T12:03:59+05:30"
    },
    {
      "name": "swetha",
      "phone": "9535116953",
      "owner": "Neha Aziz",
      "leadStatus": "Attempted Contact",
      "leadSubStatus": "NC 1",
      "createdTime": "2026-02-24T10:37:23+05:30",
      "called": true,
      "modifiedTime": "2026-02-24T11:27:52+05:30"
    },
    {
      "name": "Incoming Call Lead",
      "phone": "9845077639",
      "owner": "Anuj Polladia",
      "leadStatus": "Rejected",
      "leadSubStatus": "Just Enquiring",
      "createdTime": "2026-02-24T10:31:21+05:30",
      "called": true,
      "modifiedTime": "2026-02-24T10:32:59+05:30"
    },
    {
      "name": "Incoming Call Lead",
      "phone": "9844532111",
      "owner": "Himasri",
      "leadStatus": "Contacted",
      "leadSubStatus": "Call Back Later",
      "createdTime": "2026-02-24T10:27:52+05:30",
      "called": true,
      "modifiedTime": "2026-02-24T11:05:20+05:30"
    },
    {
      "name": "Madan Khadka",
      "phone": "9611676020",
      "owner": "Rith Tamang",
      "leadStatus": "Rejected",
      "leadSubStatus": "Service Not Available",
      "createdTime": "2026-02-24T10:16:23+05:30",
      "called": true,
      "modifiedTime": "2026-02-24T11:22:26+05:30"
    },
    {
      "name": "Incoming Call Lead",
      "phone": "9845110363",
      "owner": "Neha Aziz",
      "leadStatus": "Attempted Contact",
      "leadSubStatus": "NC 1",
      "createdTime": "2026-02-24T10:16:09+05:30",
      "called": true,
      "modifiedTime": "2026-02-24T12:48:58+05:30"
    },
    {
      "name": "Incoming Call Lead",
      "phone": "9742171990",
      "owner": "Neha Aziz",
      "leadStatus": "Contacted",
      "leadSubStatus": "Call Back Later",
      "createdTime": "2026-02-24T10:06:44+05:30",
      "called": true,
      "modifiedTime": "2026-02-24T10:13:02+05:30"
    },
    {
      "name": "Shreya Gupta",
      "phone": "9983776784",
      "owner": "Rani KJ",
      "leadStatus": "Rejected",
      "leadSubStatus": "Just Enquiring",
      "createdTime": "2026-02-24T09:59:53+05:30",
      "called": true,
      "modifiedTime": "2026-02-24T13:48:01+05:30"
    },
    {
      "name": "Incoming Call Lead",
      "phone": "1439437291",
      "owner": "Himasri",
      "leadStatus": "Rejected",
      "leadSubStatus": "Just Enquiring",
      "createdTime": "2026-02-24T09:54:14+05:30",
      "called": true,
      "modifiedTime": "2026-02-24T11:11:18+05:30"
    },
    {
      "name": "Incoming Call Lead",
      "phone": "8722223344",
      "owner": "Shahin BR",
      "leadStatus": "Attempted Contact",
      "leadSubStatus": "NC 3",
      "createdTime": "2026-02-24T09:44:06+05:30",
      "called": true,
      "modifiedTime": "2026-02-24T11:33:08+05:30"
    },
    {
      "name": "Incoming Call Lead",
      "phone": "7894646685",
      "owner": "Rani KJ",
      "leadStatus": "Rejected",
      "leadSubStatus": "Service Not Available",
      "createdTime": "2026-02-24T09:38:06+05:30",
      "called": true,
      "modifiedTime": "2026-02-24T09:48:54+05:30"
    },
    {
      "name": "Sameer",
      "phone": "6389789268",
      "owner": "Rith Tamang",
      "leadStatus": "Open Leads",
      "leadSubStatus": "Not Contacted",
      "createdTime": "2026-02-24T09:30:23+05:30",
      "called": false,
      "modifiedTime": "2026-02-24T09:30:23+05:30"
    },
    {
      "name": "Kandra Saravana Kumar",
      "phone": "9959995552",
      "owner": "Neha Aziz",
      "leadStatus": "Attempted Contact",
      "leadSubStatus": "NC 1",
      "createdTime": "2026-02-24T09:24:23+05:30",
      "called": true,
      "modifiedTime": "2026-02-24T12:47:25+05:30"
    },
    {
      "name": "Halesh",
      "phone": "9900907292",
      "owner": "Himasri",
      "leadStatus": "Rejected",
      "leadSubStatus": "Just Enquiring",
      "createdTime": "2026-02-24T09:17:52+05:30",
      "called": true,
      "modifiedTime": "2026-02-24T09:30:31+05:30"
    },
    {
      "name": "Incoming Call Lead",
      "phone": "9380364859",
      "owner": "Himasri",
      "leadStatus": "Rejected",
      "leadSubStatus": "Just Enquiring",
      "createdTime": "2026-02-24T09:11:58+05:30",
      "called": true,
      "modifiedTime": "2026-02-24T10:05:18+05:30"
    },
    {
      "name": "Chetali samant",
      "phone": "09482689840",
      "owner": "Pardeep Kumar",
      "leadStatus": "Open Leads",
      "leadSubStatus": "Not Contacted",
      "createdTime": "2026-02-24T09:00:52+05:30",
      "called": false,
      "modifiedTime": "2026-02-24T09:00:52+05:30"
    },
    {
      "name": "Incoming Call Lead",
      "phone": "9451751751",
      "owner": "Neha Aziz",
      "leadStatus": "Contacted",
      "leadSubStatus": "Call Back Later",
      "createdTime": "2026-02-24T08:46:17+05:30",
      "called": true,
      "modifiedTime": "2026-02-24T10:07:01+05:30"
    },
    {
      "name": "Incoming Call Lead",
      "phone": "8861716467",
      "owner": "Neha Aziz",
      "leadStatus": "Rejected",
      "leadSubStatus": "Duplicate",
      "createdTime": "2026-02-24T08:41:06+05:30",
      "called": true,
      "modifiedTime": "2026-02-24T09:59:49+05:30"
    },
    {
      "name": "Bharath Kumar",
      "phone": "8744044418",
      "owner": "Rith Tamang",
      "leadStatus": "Rejected",
      "leadSubStatus": "Just Enquiring",
      "createdTime": "2026-02-24T08:35:22+05:30",
      "called": true,
      "modifiedTime": "2026-02-24T08:42:44+05:30"
    },
    {
      "name": "Incoming Call Lead",
      "phone": "9972293300",
      "owner": "Rani KJ",
      "leadStatus": "Rejected",
      "leadSubStatus": "Just Enquiring",
      "createdTime": "2026-02-24T08:23:31+05:30",
      "called": true,
      "modifiedTime": "2026-02-24T08:36:46+05:30"
    },
    {
      "name": "Vignesh",
      "phone": "7708823224",
      "owner": "Rani KJ",
      "leadStatus": "Rejected",
      "leadSubStatus": "Just Enquiring",
      "createdTime": "2026-02-24T08:20:52+05:30",
      "called": true,
      "modifiedTime": "2026-02-24T12:14:37+05:30"
    },
    {
      "name": "Incoming Call Lead",
      "phone": "9494413348",
      "owner": "Neha Aziz",
      "leadStatus": "Contacted",
      "leadSubStatus": "Call Back Later",
      "createdTime": "2026-02-24T08:16:46+05:30",
      "called": true,
      "modifiedTime": "2026-02-24T09:58:18+05:30"
    },
    {
      "name": "Kasinadha",
      "phone": "8884723666",
      "owner": "Rajeswari R",
      "leadStatus": "Rejected",
      "leadSubStatus": "Just Enquiring",
      "createdTime": "2026-02-24T08:14:22+05:30",
      "called": true,
      "modifiedTime": "2026-02-24T10:04:06+05:30"
    },
    {
      "name": "Shivashankar",
      "phone": "9901666307",
      "owner": "Himasri",
      "leadStatus": "Rejected",
      "leadSubStatus": "Price is high",
      "createdTime": "2026-02-24T08:04:52+05:30",
      "called": true,
      "modifiedTime": "2026-02-24T09:28:57+05:30"
    },
    {
      "name": "Tarun Chugh",
      "phone": "9650493432",
      "owner": "Neha Aziz",
      "leadStatus": "Rejected",
      "leadSubStatus": "Just Enquiring",
      "createdTime": "2026-02-24T07:30:22+05:30",
      "called": true,
      "modifiedTime": "2026-02-24T08:55:48+05:30"
    },
    {
      "name": "Kiran B G",
      "phone": "8147513193",
      "owner": "Rith Tamang",
      "leadStatus": "Rejected",
      "leadSubStatus": "Out Of Service Area",
      "createdTime": "2026-02-24T07:16:52+05:30",
      "called": true,
      "modifiedTime": "2026-02-24T08:07:32+05:30"
    },
    {
      "name": "Janakiram reddy",
      "phone": "8686386564",
      "owner": "Pardeep Kumar",
      "leadStatus": "Open Leads",
      "leadSubStatus": "Not Contacted",
      "createdTime": "2026-02-24T07:06:22+05:30",
      "called": false,
      "modifiedTime": "2026-02-24T07:06:22+05:30"
    },
    {
      "name": "Unnikrishnan A",
      "phone": "9738030133",
      "owner": "Reshma Reddy",
      "leadStatus": "Rejected",
      "leadSubStatus": "Just Enquiring",
      "createdTime": "2026-02-24T06:37:52+05:30",
      "called": true,
      "modifiedTime": "2026-02-24T13:16:33+05:30"
    },
    {
      "name": "Ramanan T",
      "phone": "9741351513",
      "owner": "Neha Aziz",
      "leadStatus": "Attempted Contact",
      "leadSubStatus": "NC 1",
      "createdTime": "2026-02-24T06:33:52+05:30",
      "called": true,
      "modifiedTime": "2026-02-24T08:58:42+05:30"
    },
    {
      "name": "NIRMAL SINGH",
      "phone": "+917889794629",
      "owner": "Vineeth Wankhade",
      "leadStatus": "Open Leads",
      "leadSubStatus": "Not Contacted",
      "createdTime": "2026-02-24T05:56:34+05:30",
      "called": true,
      "modifiedTime": "2026-02-24T10:27:04+05:30"
    },
    {
      "name": "Akila Krishnamoorthy",
      "phone": "9900925787",
      "owner": "Rajeswari R",
      "leadStatus": "Open Leads",
      "leadSubStatus": "Not Contacted",
      "createdTime": "2026-02-24T05:56:22+05:30",
      "called": true,
      "modifiedTime": "2026-02-24T14:00:21+05:30"
    },
    {
      "name": "Ad Studio",
      "phone": "+919538274333",
      "owner": "Vineeth Wankhade",
      "leadStatus": "Open Leads",
      "leadSubStatus": "Not Contacted",
      "createdTime": "2026-02-24T05:41:40+05:30",
      "called": true,
      "modifiedTime": "2026-02-24T09:24:01+05:30"
    },
    {
      "name": "Shaik touhid",
      "phone": "8548814923",
      "owner": "Rith Tamang",
      "leadStatus": "Attempted Contact",
      "leadSubStatus": "NC 1",
      "createdTime": "2026-02-24T03:27:51+05:30",
      "called": true,
      "modifiedTime": "2026-02-24T09:00:37+05:30"
    },
    {
      "name": "Sneha",
      "phone": "6001856775",
      "owner": "Pardeep Kumar",
      "leadStatus": "Open Leads",
      "leadSubStatus": "Not Contacted",
      "createdTime": "2026-02-24T03:11:21+05:30",
      "called": false,
      "modifiedTime": "2026-02-24T03:11:21+05:30"
    },
    {
      "name": "Noor Ayesha",
      "phone": "6364302127",
      "owner": "Himasri",
      "leadStatus": "Attempted Contact",
      "leadSubStatus": "NC 1",
      "createdTime": "2026-02-24T02:20:21+05:30",
      "called": true,
      "modifiedTime": "2026-02-24T09:33:40+05:30"
    },
    {
      "name": "Suresh",
      "phone": "7760498300",
      "owner": "Pardeep Kumar",
      "leadStatus": "Open Leads",
      "leadSubStatus": "Not Contacted",
      "createdTime": "2026-02-24T01:39:50+05:30",
      "called": false,
      "modifiedTime": "2026-02-24T01:39:50+05:30"
    },
    {
      "name": "Pranjal",
      "phone": "9971797444",
      "owner": "Rani KJ",
      "leadStatus": "Rejected",
      "leadSubStatus": "Just Enquiring",
      "createdTime": "2026-02-24T00:06:20+05:30",
      "called": true,
      "modifiedTime": "2026-02-24T12:21:20+05:30"
    },
    {
      "name": "Archana",
      "phone": "09573680660",
      "owner": "Pardeep Kumar",
      "leadStatus": "Open Leads",
      "leadSubStatus": "Not Contacted",
      "createdTime": "2026-02-23T23:30:19+05:30",
      "called": false,
      "modifiedTime": "2026-02-23T23:30:19+05:30"
    },
    {
      "name": "Amit Singh",
      "phone": "+919711463680",
      "owner": "Rith Tamang",
      "leadStatus": "Attempted Contact",
      "leadSubStatus": "NC 1",
      "createdTime": "2026-02-23T22:17:08+05:30",
      "called": true,
      "modifiedTime": "2026-02-24T09:04:52+05:30"
    },
    {
      "name": "Sharan",
      "phone": "9663530396",
      "owner": "Neha Aziz",
      "leadStatus": "Rejected",
      "leadSubStatus": "Out Of Service Area",
      "createdTime": "2026-02-23T21:45:15+05:30",
      "called": true,
      "modifiedTime": "2026-02-24T10:18:19+05:30"
    },
    {
      "name": "Rahul",
      "phone": "9599891607",
      "owner": "Rani KJ",
      "leadStatus": "Rejected",
      "leadSubStatus": "Out Of Service Area",
      "createdTime": "2026-02-23T21:43:19+05:30",
      "called": true,
      "modifiedTime": "2026-02-24T09:11:19+05:30"
    },
    {
      "name": "Incoming Call Lead",
      "phone": "9677846627",
      "owner": "Rith Tamang",
      "leadStatus": "Attempted Contact",
      "leadSubStatus": "NC 1",
      "createdTime": "2026-02-23T21:25:12+05:30",
      "called": true,
      "modifiedTime": "2026-02-24T08:22:33+05:30"
    },
    {
      "name": "SINDHU SUNIL",
      "phone": "9035253079",
      "owner": "Neha Aziz",
      "leadStatus": "Attempted Contact",
      "leadSubStatus": "NC 1",
      "createdTime": "2026-02-23T21:20:10+05:30",
      "called": true,
      "modifiedTime": "2026-02-24T09:52:11+05:30"
    },
    {
      "name": "Incoming Call Lead",
      "phone": "9853046234",
      "owner": "Rani KJ",
      "leadStatus": "Rejected",
      "leadSubStatus": "Service Not Available",
      "createdTime": "2026-02-23T21:15:09+05:30",
      "called": true,
      "modifiedTime": "2026-02-24T10:05:24+05:30"
    },
    {
      "name": "Gautam",
      "phone": "+916398137650",
      "owner": "Neha Aziz",
      "leadStatus": "Attempted Contact",
      "leadSubStatus": "NC 1",
      "createdTime": "2026-02-23T21:11:54+05:30",
      "called": true,
      "modifiedTime": "2026-02-24T09:53:33+05:30"
    },
    {
      "name": "Gowri",
      "phone": "9884422804",
      "owner": "Himasri",
      "leadStatus": "Rejected",
      "leadSubStatus": "Just Enquiring",
      "createdTime": "2026-02-23T20:44:18+05:30",
      "called": true,
      "modifiedTime": "2026-02-24T09:26:00+05:30"
    },
    {
      "name": "Incoming Call Lead",
      "phone": "9341979732",
      "owner": "Anuj Polladia",
      "leadStatus": "Rejected",
      "leadSubStatus": "Price is high",
      "createdTime": "2026-02-23T20:35:01+05:30",
      "called": true,
      "modifiedTime": "2026-02-24T09:38:01+05:30"
    },
    {
      "name": "Keerthana",
      "phone": "9445948722",
      "owner": "Amala",
      "leadStatus": "Open Leads",
      "leadSubStatus": "Not Contacted",
      "createdTime": "2026-02-23T20:31:48+05:30",
      "called": true,
      "modifiedTime": "2026-02-24T14:00:23+05:30"
    },
    {
      "name": "Incoming Call Lead",
      "phone": "9738333324",
      "owner": "Neha Aziz",
      "leadStatus": "Contacted",
      "leadSubStatus": "Call Back Later",
      "createdTime": "2026-02-23T20:04:51+05:30",
      "called": true,
      "modifiedTime": "2026-02-24T09:03:41+05:30"
    },
    {
      "name": "Incoming Call Lead",
      "phone": "9108355099",
      "owner": "Anuj Polladia",
      "leadStatus": "Rejected",
      "leadSubStatus": "Just Enquiring",
      "createdTime": "2026-02-23T19:29:48+05:30",
      "called": true,
      "modifiedTime": "2026-02-23T19:30:15+05:30"
    },
    {
      "name": "Arbiya",
      "phone": "9916728629",
      "owner": "Neha Aziz",
      "leadStatus": "Rejected",
      "leadSubStatus": "Just Enquiring",
      "createdTime": "2026-02-23T19:28:48+05:30",
      "called": true,
      "modifiedTime": "2026-02-24T09:46:23+05:30"
    },
    {
      "name": "Incoming Call Lead",
      "phone": "9900783770",
      "owner": "Anuj Polladia",
      "leadStatus": "Rejected",
      "leadSubStatus": "Just Enquiring",
      "createdTime": "2026-02-23T19:26:18+05:30",
      "called": true,
      "modifiedTime": "2026-02-23T19:26:59+05:30"
    },
    {
      "name": "Jagadeesh",
      "phone": "9629108624",
      "owner": "Anuj Polladia",
      "leadStatus": "Rejected",
      "leadSubStatus": "Wrong Number",
      "createdTime": "2026-02-23T19:19:18+05:30",
      "called": true,
      "modifiedTime": "2026-02-23T19:23:26+05:30"
    },
    {
      "name": "Incoming Call Lead",
      "phone": "9886022669",
      "owner": "Neha Aziz",
      "leadStatus": "Rejected",
      "leadSubStatus": "Just Enquiring",
      "createdTime": "2026-02-23T19:09:45+05:30",
      "called": true,
      "modifiedTime": "2026-02-23T19:45:15+05:30"
    },
    {
      "name": "Incoming Call Lead",
      "phone": "9731730500",
      "owner": "Rani KJ",
      "leadStatus": "Rejected",
      "leadSubStatus": "Not Answering",
      "createdTime": "2026-02-23T19:09:44+05:30",
      "called": true,
      "modifiedTime": "2026-02-24T12:12:00+05:30"
    },
    {
      "name": "Incoming Call Lead",
      "phone": "9606060602",
      "owner": "Anuj Polladia",
      "leadStatus": "Rejected",
      "leadSubStatus": "Just Enquiring",
      "createdTime": "2026-02-23T19:04:50+05:30",
      "called": true,
      "modifiedTime": "2026-02-23T19:05:25+05:30"
    },
    {
      "name": "Incoming Call Lead",
      "phone": "9035313024",
      "owner": "Neha Aziz",
      "leadStatus": "Contacted",
      "leadSubStatus": "Call Back Later",
      "createdTime": "2026-02-23T19:04:01+05:30",
      "called": true,
      "modifiedTime": "2026-02-23T19:45:57+05:30"
    },
    {
      "name": "Incoming Call Lead",
      "phone": "9901788455",
      "owner": "Anuj Polladia",
      "leadStatus": "Rejected",
      "leadSubStatus": "Just Enquiring",
      "createdTime": "2026-02-23T18:50:49+05:30",
      "called": true,
      "modifiedTime": "2026-02-23T18:52:17+05:30"
    },
    {
      "name": "Aritro Maity",
      "phone": "9330155060",
      "owner": "Neha Aziz",
      "leadStatus": "Attempted Contact",
      "leadSubStatus": "NC 1",
      "createdTime": "2026-02-23T18:50:17+05:30",
      "called": true,
      "modifiedTime": "2026-02-24T10:08:24+05:30"
    },
    {
      "name": "Incoming Call Lead",
      "phone": "9164078641",
      "owner": "Rani KJ",
      "leadStatus": "Rejected",
      "leadSubStatus": "Service Not Available",
      "createdTime": "2026-02-23T18:49:41+05:30",
      "called": true,
      "modifiedTime": "2026-02-24T14:05:09+05:30"
    },
    {
      "name": "Incoming Call Lead",
      "phone": "9663639683",
      "owner": "Anuj Polladia",
      "leadStatus": "Rejected",
      "leadSubStatus": "Just Enquiring",
      "createdTime": "2026-02-23T18:40:22+05:30",
      "called": true,
      "modifiedTime": "2026-02-23T18:47:36+05:30"
    },
    {
      "name": "Shivananda",
      "phone": "9962455571",
      "owner": "Anuj Polladia",
      "leadStatus": "Open Leads",
      "leadSubStatus": "Not Contacted",
      "createdTime": "2026-02-23T18:36:17+05:30",
      "called": true,
      "modifiedTime": "2026-02-23T18:38:47+05:30"
    },
    {
      "name": "Incoming Call Lead",
      "phone": "9958295443",
      "owner": "Anuj Polladia",
      "leadStatus": "Rejected",
      "leadSubStatus": "Just Enquiring",
      "createdTime": "2026-02-23T18:29:42+05:30",
      "called": true,
      "modifiedTime": "2026-02-23T18:30:27+05:30"
    },
    {
      "name": "Incoming Call Lead",
      "phone": "8095982863",
      "owner": "Anuj Polladia",
      "leadStatus": "Rejected",
      "leadSubStatus": "Just Enquiring",
      "createdTime": "2026-02-23T18:09:51+05:30",
      "called": true,
      "modifiedTime": "2026-02-23T18:10:51+05:30"
    },
    {
      "name": "Meghana",
      "phone": "9481987738",
      "owner": "Rith Tamang",
      "leadStatus": "Rejected",
      "leadSubStatus": "Just Enquiring",
      "createdTime": "2026-02-23T18:05:17+05:30",
      "called": true,
      "modifiedTime": "2026-02-24T08:32:22+05:30"
    },
    {
      "name": "Kempe gowda",
      "phone": "8861224572",
      "owner": "Shahin BR",
      "leadStatus": "Rejected",
      "leadSubStatus": "Price is high",
      "createdTime": "2026-02-23T18:01:17+05:30",
      "called": true,
      "modifiedTime": "2026-02-23T19:00:26+05:30"
    },
    {
      "name": "Rahul Gowda",
      "phone": "9902342637",
      "owner": "Himasri",
      "leadStatus": "Attempted Contact",
      "leadSubStatus": "NC 1",
      "createdTime": "2026-02-23T17:45:47+05:30",
      "called": true,
      "modifiedTime": "2026-02-24T10:32:22+05:30"
    },
    {
      "name": "Incoming Call Lead",
      "phone": "8217874418",
      "owner": "Neha Aziz",
      "leadStatus": "Contacted",
      "leadSubStatus": "Call Back Later",
      "createdTime": "2026-02-23T17:35:45+05:30",
      "called": true,
      "modifiedTime": "2026-02-24T09:10:54+05:30"
    },
    {
      "name": "Incoming Call Lead",
      "phone": "9845588440",
      "owner": "Himasri",
      "leadStatus": "Contacted",
      "leadSubStatus": "Call Back Later",
      "createdTime": "2026-02-23T17:35:22+05:30",
      "called": true,
      "modifiedTime": "2026-02-23T19:46:35+05:30"
    },
    {
      "name": "Incoming Call Lead",
      "phone": "9175146346",
      "owner": "Himasri",
      "leadStatus": "Contacted",
      "leadSubStatus": "Call Back Later",
      "createdTime": "2026-02-23T17:18:37+05:30",
      "called": true,
      "modifiedTime": "2026-02-24T09:02:56+05:30"
    },
    {
      "name": "Nagaraj Mysore",
      "phone": "9845090785",
      "owner": "Rajeswari R",
      "leadStatus": "Attempted Contact",
      "leadSubStatus": "NC 1",
      "createdTime": "2026-02-23T17:17:47+05:30",
      "called": true,
      "modifiedTime": "2026-02-23T17:21:43+05:30"
    },
    {
      "name": "Incoming Call Lead",
      "phone": "9820172057",
      "owner": "Neha Aziz",
      "leadStatus": "Rejected",
      "leadSubStatus": "Just Enquiring",
      "createdTime": "2026-02-23T16:57:36+05:30",
      "called": true,
      "modifiedTime": "2026-02-23T17:06:45+05:30"
    },
    {
      "name": "Sidhartha",
      "phone": "9966077667",
      "owner": "Rani KJ",
      "leadStatus": "Rejected",
      "leadSubStatus": "Booked From Others",
      "createdTime": "2026-02-23T16:50:16+05:30",
      "called": true,
      "modifiedTime": "2026-02-24T10:29:44+05:30"
    },
    {
      "name": "ANIL KUMAR",
      "phone": "9742258521",
      "owner": "Neha Aziz",
      "leadStatus": "Attempted Contact",
      "leadSubStatus": "NC 1",
      "createdTime": "2026-02-23T16:34:46+05:30",
      "called": true,
      "modifiedTime": "2026-02-24T09:44:49+05:30"
    },
    {
      "name": "Incoming Call Lead",
      "phone": "6364039876",
      "owner": "Rajeswari R",
      "leadStatus": "Rejected",
      "leadSubStatus": "Out Of Service Area",
      "createdTime": "2026-02-23T16:29:01+05:30",
      "called": true,
      "modifiedTime": "2026-02-23T16:35:45+05:30"
    },
    {
      "name": "Jeevan",
      "phone": "79-75374858",
      "owner": "Rith Tamang",
      "leadStatus": "Rejected",
      "leadSubStatus": "Just Enquiring",
      "createdTime": "2026-02-23T16:19:15+05:30",
      "called": true,
      "modifiedTime": "2026-02-23T16:22:39+05:30"
    },
    {
      "name": "Mr Charu Jain",
      "phone": "9999173406",
      "owner": "Neha Aziz",
      "leadStatus": "Contacted",
      "leadSubStatus": "Call Back Later",
      "createdTime": "2026-02-23T16:10:09+05:30",
      "called": true,
      "modifiedTime": "2026-02-23T16:19:10+05:30"
    },
    {
      "name": "Incoming Call Lead",
      "phone": "9632679914",
      "owner": "Himasri",
      "leadStatus": "Contacted",
      "leadSubStatus": "Call Back Later",
      "createdTime": "2026-02-23T16:06:02+05:30",
      "called": true,
      "modifiedTime": "2026-02-23T19:06:03+05:30"
    },
    {
      "name": "MadhaVi",
      "phone": "7795521544",
      "owner": "Rajeswari R",
      "leadStatus": "Attempted Contact",
      "leadSubStatus": "NC 1",
      "createdTime": "2026-02-23T15:59:45+05:30",
      "called": true,
      "modifiedTime": "2026-02-23T17:22:17+05:30"
    },
    {
      "name": "Altaf Khan",
      "phone": "9820000005",
      "owner": "Neha Aziz",
      "leadStatus": "Contacted",
      "leadSubStatus": "Call Back Later",
      "createdTime": "2026-02-23T15:53:15+05:30",
      "called": true,
      "modifiedTime": "2026-02-23T16:15:51+05:30"
    },
    {
      "name": "Incoming Call Lead",
      "phone": "8296715556",
      "owner": "Rajeswari R",
      "leadStatus": "Rejected",
      "leadSubStatus": "Just Enquiring",
      "createdTime": "2026-02-23T15:49:45+05:30",
      "called": true,
      "modifiedTime": "2026-02-23T15:50:04+05:30"
    },
    {
      "name": "Incoming Call Lead",
      "phone": "9900435588",
      "owner": "Rani KJ",
      "leadStatus": "Rejected",
      "leadSubStatus": "Service Not Available",
      "createdTime": "2026-02-23T15:43:20+05:30",
      "called": true,
      "modifiedTime": "2026-02-23T16:02:57+05:30"
    },
    {
      "name": "Smruti Mishra",
      "phone": "8147062129",
      "owner": "Rani KJ",
      "leadStatus": "Open Leads",
      "leadSubStatus": "Not Contacted",
      "createdTime": "2026-02-23T15:35:15+05:30",
      "called": false,
      "modifiedTime": "2026-02-23T15:35:15+05:30"
    },
    {
      "name": "niraj",
      "phone": "9035894801",
      "owner": "Rajeswari R",
      "leadStatus": "Attempted Contact",
      "leadSubStatus": "NC 2",
      "createdTime": "2026-02-23T15:25:45+05:30",
      "called": true,
      "modifiedTime": "2026-02-23T16:21:48+05:30"
    },
    {
      "name": "Nagarathna",
      "phone": "9740359380",
      "owner": "Rith Tamang",
      "leadStatus": "Attempted Contact",
      "leadSubStatus": "NC 1",
      "createdTime": "2026-02-23T15:20:15+05:30",
      "called": true,
      "modifiedTime": "2026-02-24T08:23:43+05:30"
    },
    {
      "name": "Incoming Call Lead",
      "phone": "9008827539",
      "owner": "Rani KJ",
      "leadStatus": "Rejected",
      "leadSubStatus": "Just Enquiring",
      "createdTime": "2026-02-23T15:13:10+05:30",
      "called": true,
      "modifiedTime": "2026-02-23T15:19:23+05:30"
    },
    {
      "name": "Incoming Call Lead",
      "phone": "9986079924",
      "owner": "Rajeswari R",
      "leadStatus": "Rejected",
      "leadSubStatus": "Price is high",
      "createdTime": "2026-02-23T15:09:32+05:30",
      "called": true,
      "modifiedTime": "2026-02-23T15:10:49+05:30"
    },
    {
      "name": "Karthik",
      "phone": "9894386955",
      "owner": "Himasri",
      "leadStatus": "Open Leads",
      "leadSubStatus": "Not Contacted",
      "createdTime": "2026-02-23T15:04:17+05:30",
      "called": true,
      "modifiedTime": "2026-02-23T15:08:44+05:30"
    },
    {
      "name": "Incoming Call Lead",
      "phone": "9241103033",
      "owner": "Rith Tamang",
      "leadStatus": "Rejected",
      "leadSubStatus": "Price is high",
      "createdTime": "2026-02-23T14:55:17+05:30",
      "called": true,
      "modifiedTime": "2026-02-23T14:59:30+05:30"
    },
    {
      "name": "Diljit",
      "phone": "08085679092",
      "owner": "Pardeep Kumar",
      "leadStatus": "Open Leads",
      "leadSubStatus": "Not Contacted",
      "createdTime": "2026-02-23T14:54:14+05:30",
      "called": true,
      "modifiedTime": "2026-02-23T14:57:44+05:30"
    },
    {
      "name": "Incoming Call Lead",
      "phone": "8252699423",
      "owner": "Neha Aziz",
      "leadStatus": "Rejected",
      "leadSubStatus": "Just Enquiring",
      "createdTime": "2026-02-23T14:44:41+05:30",
      "called": true,
      "modifiedTime": "2026-02-23T14:52:44+05:30"
    },
    {
      "name": "Abhishek Kumar",
      "phone": "09980621240",
      "owner": "Neha Aziz",
      "leadStatus": "Rejected",
      "leadSubStatus": "Service Not Available",
      "createdTime": "2026-02-23T14:37:44+05:30",
      "called": true,
      "modifiedTime": "2026-02-23T14:42:00+05:30"
    },
    {
      "name": "Ayesha",
      "phone": "8310846582",
      "owner": "Rani KJ",
      "leadStatus": "Rejected",
      "leadSubStatus": "Price is high",
      "createdTime": "2026-02-23T14:29:44+05:30",
      "called": true,
      "modifiedTime": "2026-02-23T14:58:26+05:30"
    },
    {
      "name": "Incoming Call Lead",
      "phone": "9980795333",
      "owner": "Rani KJ",
      "leadStatus": "Rejected",
      "leadSubStatus": "Just Enquiring",
      "createdTime": "2026-02-23T14:27:00+05:30",
      "called": true,
      "modifiedTime": "2026-02-23T14:30:31+05:30"
    },
    {
      "name": "Vaishnavi",
      "phone": "9821089191",
      "owner": "Rajeswari R",
      "leadStatus": "Attempted Contact",
      "leadSubStatus": "NC 2",
      "createdTime": "2026-02-23T14:23:44+05:30",
      "called": true,
      "modifiedTime": "2026-02-23T16:21:07+05:30"
    },
    {
      "name": "Nitin Lunia",
      "phone": "+919243445444",
      "owner": "Vineeth Wankhade",
      "leadStatus": "Open Leads",
      "leadSubStatus": "Not Contacted",
      "createdTime": "2026-02-23T14:21:56+05:30",
      "called": true,
      "modifiedTime": "2026-02-23T14:54:21+05:30"
    },
    {
      "name": "Incoming Call Lead",
      "phone": "9916376738",
      "owner": "Neha Aziz",
      "leadStatus": "Rejected",
      "leadSubStatus": "Just Enquiring",
      "createdTime": "2026-02-23T14:17:53+05:30",
      "called": true,
      "modifiedTime": "2026-02-23T14:45:49+05:30"
    },
    {
      "name": "Incoming Call Lead",
      "phone": "9845844681",
      "owner": "Himasri",
      "leadStatus": "Contacted",
      "leadSubStatus": "Call Back Later",
      "createdTime": "2026-02-23T14:16:56+05:30",
      "called": true,
      "modifiedTime": "2026-02-23T19:47:23+05:30"
    },
    {
      "name": "Incoming Call Lead",
      "phone": "9448988528",
      "owner": "Himasri",
      "leadStatus": "Contacted",
      "leadSubStatus": "Call Back Later",
      "createdTime": "2026-02-23T14:13:44+05:30",
      "called": true,
      "modifiedTime": "2026-02-23T14:27:21+05:30"
    },
    {
      "name": "Mani",
      "phone": "7012631165",
      "owner": "Rajeswari R",
      "leadStatus": "Rejected",
      "leadSubStatus": "Price is high",
      "createdTime": "2026-02-23T14:13:44+05:30",
      "called": true,
      "modifiedTime": "2026-02-23T16:05:54+05:30"
    },
    {
      "name": "Incoming Call Lead",
      "phone": "7760468438",
      "owner": "Himasri",
      "leadStatus": "Contacted",
      "leadSubStatus": "Call Back Later",
      "createdTime": "2026-02-23T14:13:21+05:30",
      "called": true,
      "modifiedTime": "2026-02-23T20:01:05+05:30"
    },
    {
      "name": "Incoming Call Lead",
      "phone": "9731860732",
      "owner": "Rith Tamang",
      "leadStatus": "Rejected",
      "leadSubStatus": "Just Enquiring",
      "createdTime": "2026-02-23T14:12:30+05:30",
      "called": true,
      "modifiedTime": "2026-02-23T14:49:13+05:30"
    },
    {
      "name": "Incoming Call Lead",
      "phone": "7921228378",
      "owner": "Neha Aziz",
      "leadStatus": "Attempted Contact",
      "leadSubStatus": "NC 1",
      "createdTime": "2026-02-23T14:08:43+05:30",
      "called": true,
      "modifiedTime": "2026-02-23T14:45:17+05:30"
    },
    {
      "name": "Incoming Call Lead",
      "phone": "9902344217",
      "owner": "Neha Aziz",
      "leadStatus": "Attempted Contact",
      "leadSubStatus": "NC 1",
      "createdTime": "2026-02-23T13:54:51+05:30",
      "called": true,
      "modifiedTime": "2026-02-23T20:27:01+05:30"
    },
    {
      "name": "Dheeraj KrishnaMurthy",
      "phone": "+919901137000",
      "owner": "Pardeep Kumar",
      "leadStatus": "Open Leads",
      "leadSubStatus": "Not Contacted",
      "createdTime": "2026-02-23T13:48:49+05:30",
      "called": true,
      "modifiedTime": "2026-02-24T14:13:38+05:30"
    },
    {
      "name": "Incoming Call Lead",
      "phone": "8861287320",
      "owner": "Rajeswari R",
      "leadStatus": "Rejected",
      "leadSubStatus": "Service Not Available",
      "createdTime": "2026-02-23T13:40:38+05:30",
      "called": true,
      "modifiedTime": "2026-02-23T13:41:01+05:30"
    },
    {
      "name": "Incoming Call Lead",
      "phone": "9341233722",
      "owner": "Rith Tamang",
      "leadStatus": "Rejected",
      "leadSubStatus": "Just Enquiring",
      "createdTime": "2026-02-23T13:35:18+05:30",
      "called": true,
      "modifiedTime": "2026-02-23T13:47:16+05:30"
    },
    {
      "name": "Divya K Menon",
      "phone": "+918805025893",
      "owner": "Rajeswari R",
      "leadStatus": "Open Leads",
      "leadSubStatus": "Not Contacted",
      "createdTime": "2026-02-23T13:33:52+05:30",
      "called": true,
      "modifiedTime": "2026-02-23T13:41:47+05:30"
    },
    {
      "name": "H Ramakrishnaiah",
      "phone": "9538154455",
      "owner": "Pardeep Kumar",
      "leadStatus": "Open Leads",
      "leadSubStatus": "Not Contacted",
      "createdTime": "2026-02-23T13:32:44+05:30",
      "called": false,
      "modifiedTime": "2026-02-23T13:32:44+05:30"
    },
    {
      "name": "Incoming Call Lead",
      "phone": "9036823904",
      "owner": "Neha Aziz",
      "leadStatus": "Rejected",
      "leadSubStatus": "Just Enquiring",
      "createdTime": "2026-02-23T13:29:32+05:30",
      "called": true,
      "modifiedTime": "2026-02-23T13:42:10+05:30"
    },
    {
      "name": "Incoming Call Lead",
      "phone": "9342574641",
      "owner": "Himasri",
      "leadStatus": "Rejected",
      "leadSubStatus": "Just Enquiring",
      "createdTime": "2026-02-23T13:26:37+05:30",
      "called": true,
      "modifiedTime": "2026-02-23T13:48:13+05:30"
    },
    {
      "name": "Praveen",
      "phone": "9063086861",
      "owner": "Pardeep Kumar",
      "leadStatus": "Open Leads",
      "leadSubStatus": "Not Contacted",
      "createdTime": "2026-02-23T13:21:14+05:30",
      "called": false,
      "modifiedTime": "2026-02-23T13:21:14+05:30"
    },
    {
      "name": "Incoming Call Lead",
      "phone": "9361171125",
      "owner": "Rani KJ",
      "leadStatus": "Rejected",
      "leadSubStatus": "Just Enquiring",
      "createdTime": "2026-02-23T13:21:05+05:30",
      "called": true,
      "modifiedTime": "2026-02-23T13:44:56+05:30"
    },
    {
      "name": "Incoming Call Lead",
      "phone": "8801051840",
      "owner": "Himasri",
      "leadStatus": "Contacted",
      "leadSubStatus": "Call Back Later",
      "createdTime": "2026-02-23T13:13:32+05:30",
      "called": true,
      "modifiedTime": "2026-02-23T13:47:27+05:30"
    },
    {
      "name": "Soujanya",
      "phone": "+919900244971",
      "owner": "Neha Aziz",
      "leadStatus": "Attempted Contact",
      "leadSubStatus": "NC 1",
      "createdTime": "2026-02-23T13:09:05+05:30",
      "called": true,
      "modifiedTime": "2026-02-23T13:43:15+05:30"
    },
    {
      "name": "Incoming Call Lead",
      "phone": "6290331616",
      "owner": "Rith Tamang",
      "leadStatus": "Rejected",
      "leadSubStatus": "Just Enquiring",
      "createdTime": "2026-02-23T13:04:26+05:30",
      "called": true,
      "modifiedTime": "2026-02-23T13:09:38+05:30"
    },
    {
      "name": "Bhuvan",
      "phone": "9886983427",
      "owner": "Himasri",
      "leadStatus": "Open Leads",
      "leadSubStatus": "Not Contacted",
      "createdTime": "2026-02-23T12:58:44+05:30",
      "called": false,
      "modifiedTime": "2026-02-23T12:58:44+05:30"
    },
    {
      "name": "kavitha nagesh",
      "phone": "9611376311",
      "owner": "Neha Aziz",
      "leadStatus": "Attempted Contact",
      "leadSubStatus": "NC 1",
      "createdTime": "2026-02-23T12:41:13+05:30",
      "called": true,
      "modifiedTime": "2026-02-24T12:45:36+05:30"
    },
    {
      "name": "Incoming Call Lead",
      "phone": "8964002950",
      "owner": "Rith Tamang",
      "leadStatus": "Rejected",
      "leadSubStatus": "Just Enquiring",
      "createdTime": "2026-02-23T12:40:20+05:30",
      "called": true,
      "modifiedTime": "2026-02-23T12:51:37+05:30"
    },
    {
      "name": "Incoming Call Lead",
      "phone": "9916170652",
      "owner": "Rajeswari R",
      "leadStatus": "Rejected",
      "leadSubStatus": "Out Of Service Area",
      "createdTime": "2026-02-23T12:34:12+05:30",
      "called": true,
      "modifiedTime": "2026-02-23T12:34:32+05:30"
    },
    {
      "name": "Bharati Poddar",
      "phone": "9831084958",
      "owner": "Neha Aziz",
      "leadStatus": "Contacted",
      "leadSubStatus": "Call Back Later",
      "createdTime": "2026-02-23T12:31:43+05:30",
      "called": true,
      "modifiedTime": "2026-02-23T12:52:45+05:30"
    },
    {
      "name": "Incoming Call Lead",
      "phone": "9945510594",
      "owner": "Himasri",
      "leadStatus": "Contacted",
      "leadSubStatus": "Call Back Later",
      "createdTime": "2026-02-23T12:28:07+05:30",
      "called": true,
      "modifiedTime": "2026-02-23T13:01:43+05:30"
    },
    {
      "name": "Incoming Call Lead",
      "phone": "9880280915",
      "owner": "Rith Tamang",
      "leadStatus": "Rejected",
      "leadSubStatus": "Just Enquiring",
      "createdTime": "2026-02-23T12:28:02+05:30",
      "called": true,
      "modifiedTime": "2026-02-23T12:28:35+05:30"
    },
    {
      "name": "Incoming Call Lead",
      "phone": "9449913000",
      "owner": "Rajeswari R",
      "leadStatus": "Rejected",
      "leadSubStatus": "Just Enquiring",
      "createdTime": "2026-02-23T12:17:54+05:30",
      "called": true,
      "modifiedTime": "2026-02-23T12:18:44+05:30"
    },
    {
      "name": "Incoming Call Lead",
      "phone": "9972528242",
      "owner": "Anuj Polladia",
      "leadStatus": "Attempted Contact",
      "leadSubStatus": "NC 1",
      "createdTime": "2026-02-23T12:13:19+05:30",
      "called": true,
      "modifiedTime": "2026-02-23T12:47:28+05:30"
    },
    {
      "name": "Incoming Call Lead",
      "phone": "9972099250",
      "owner": "Anuj Polladia",
      "leadStatus": "Rejected",
      "leadSubStatus": "Just Enquiring",
      "createdTime": "2026-02-23T12:08:18+05:30",
      "called": true,
      "modifiedTime": "2026-02-23T12:45:51+05:30"
    },
    {
      "name": "Incoming Call Lead",
      "phone": "8123135370",
      "owner": "Neha Aziz",
      "leadStatus": "Rejected",
      "leadSubStatus": "Just Enquiring",
      "createdTime": "2026-02-23T12:05:33+05:30",
      "called": true,
      "modifiedTime": "2026-02-23T15:58:30+05:30"
    },
    {
      "name": "Incoming Call Lead",
      "phone": "9008717059",
      "owner": "Reshma Reddy",
      "leadStatus": "Rejected",
      "leadSubStatus": "Just Enquiring",
      "createdTime": "2026-02-23T12:02:41+05:30",
      "called": true,
      "modifiedTime": "2026-02-23T13:03:35+05:30"
    },
    {
      "name": "Incoming Call Lead",
      "phone": "9901855288",
      "owner": "Anuj Polladia",
      "leadStatus": "Rejected",
      "leadSubStatus": "Just Enquiring",
      "createdTime": "2026-02-23T12:00:24+05:30",
      "called": true,
      "modifiedTime": "2026-02-23T12:01:23+05:30"
    },
    {
      "name": "Incoming Call Lead",
      "phone": "9008294703",
      "owner": "Rajeswari R",
      "leadStatus": "Rejected",
      "leadSubStatus": "Price is high",
      "createdTime": "2026-02-23T11:56:15+05:30",
      "called": true,
      "modifiedTime": "2026-02-23T11:56:38+05:30"
    },
    {
      "name": "Incoming Call Lead",
      "phone": "9845053425",
      "owner": "Rani KJ",
      "leadStatus": "Rejected",
      "leadSubStatus": "Just Enquiring",
      "createdTime": "2026-02-23T11:54:35+05:30",
      "called": true,
      "modifiedTime": "2026-02-23T11:55:19+05:30"
    },
    {
      "name": "Incoming Call Lead",
      "phone": "9739632525",
      "owner": "Rajeswari R",
      "leadStatus": "Rejected",
      "leadSubStatus": "Price is high",
      "createdTime": "2026-02-23T11:52:59+05:30",
      "called": true,
      "modifiedTime": "2026-02-23T11:53:14+05:30"
    },
    {
      "name": "Incoming Call Lead",
      "phone": "9019862445",
      "owner": "Anuj Polladia",
      "leadStatus": "Rejected",
      "leadSubStatus": "Just Enquiring",
      "createdTime": "2026-02-23T11:51:08+05:30",
      "called": true,
      "modifiedTime": "2026-02-23T11:52:27+05:30"
    },
    {
      "name": "Udaya Kumar A",
      "phone": "9886918151",
      "owner": "Anuj Polladia",
      "leadStatus": "Open Leads",
      "leadSubStatus": "Not Contacted",
      "createdTime": "2026-02-23T11:48:43+05:30",
      "called": false,
      "modifiedTime": "2026-02-23T11:48:43+05:30"
    },
    {
      "name": "Incoming Call Lead",
      "phone": "9777507746",
      "owner": "Anuj Polladia",
      "leadStatus": "Rejected",
      "leadSubStatus": "Just Enquiring",
      "createdTime": "2026-02-23T11:44:57+05:30",
      "called": true,
      "modifiedTime": "2026-02-23T11:51:47+05:30"
    },
    {
      "name": "Suresh",
      "phone": "+919945203306",
      "owner": "Neha Aziz",
      "leadStatus": "Rejected",
      "leadSubStatus": "Just Enquiring",
      "createdTime": "2026-02-23T11:44:18+05:30",
      "called": true,
      "modifiedTime": "2026-02-23T12:55:12+05:30"
    },
    {
      "name": "Sheetal Chandrasekharan",
      "phone": "8007205710",
      "owner": "Amala",
      "leadStatus": "Rejected",
      "leadSubStatus": "Just Enquiring",
      "createdTime": "2026-02-23T11:39:43+05:30",
      "called": true,
      "modifiedTime": "2026-02-23T12:01:17+05:30"
    },
    {
      "name": "Priya Sanni",
      "phone": "8867360249",
      "owner": "Rajeswari R",
      "leadStatus": "Attempted Contact",
      "leadSubStatus": "NC 2",
      "createdTime": "2026-02-23T11:37:13+05:30",
      "called": true,
      "modifiedTime": "2026-02-23T16:17:52+05:30"
    },
    {
      "name": "Ravi Kumar",
      "phone": "9686032281",
      "owner": "Anuj Polladia",
      "leadStatus": "Rejected",
      "leadSubStatus": "Price is high",
      "createdTime": "2026-02-23T11:31:43+05:30",
      "called": true,
      "modifiedTime": "2026-02-23T11:55:12+05:30"
    },
    {
      "name": "T Sreenivas",
      "phone": "9900097023",
      "owner": "Anuj Polladia",
      "leadStatus": "Rejected",
      "leadSubStatus": "Just Enquiring",
      "createdTime": "2026-02-23T11:30:06+05:30",
      "called": true,
      "modifiedTime": "2026-02-23T15:09:28+05:30"
    },
    {
      "name": "Incoming Call Lead",
      "phone": "9820511453",
      "owner": "Rani KJ",
      "leadStatus": "Rejected",
      "leadSubStatus": "Just Enquiring",
      "createdTime": "2026-02-23T11:28:21+05:30",
      "called": true,
      "modifiedTime": "2026-02-23T11:37:31+05:30"
    },
    {
      "name": "Incoming Call Lead",
      "phone": "9742168564",
      "owner": "Himasri",
      "leadStatus": "Rejected",
      "leadSubStatus": "Just Enquiring",
      "createdTime": "2026-02-23T11:28:13+05:30",
      "called": true,
      "modifiedTime": "2026-02-23T11:39:17+05:30"
    },
    {
      "name": "Incoming Call Lead",
      "phone": "9980222688",
      "owner": "Rajeswari R",
      "leadStatus": "Rejected",
      "leadSubStatus": "Out Of Service Area",
      "createdTime": "2026-02-23T11:26:48+05:30",
      "called": true,
      "modifiedTime": "2026-02-23T11:27:09+05:30"
    },
    {
      "name": "Incoming Call Lead",
      "phone": "7769870606",
      "owner": "Rani KJ",
      "leadStatus": "Rejected",
      "leadSubStatus": "Just Enquiring",
      "createdTime": "2026-02-23T11:21:13+05:30",
      "called": true,
      "modifiedTime": "2026-02-23T11:23:59+05:30"
    },
    {
      "name": "Incoming Call Lead",
      "phone": "9845521313",
      "owner": "Himasri",
      "leadStatus": "Rejected",
      "leadSubStatus": "Just Enquiring",
      "createdTime": "2026-02-23T11:19:07+05:30",
      "called": true,
      "modifiedTime": "2026-02-23T11:38:49+05:30"
    },
    {
      "name": "Santosh M",
      "phone": "9738527203",
      "owner": "Rajeswari R",
      "leadStatus": "Rejected",
      "leadSubStatus": "Cancelled by Customer",
      "createdTime": "2026-02-23T11:08:13+05:30",
      "called": true,
      "modifiedTime": "2026-02-23T15:04:05+05:30"
    },
    {
      "name": "Sameer Ali Waheed",
      "phone": "09980504832",
      "owner": "Himasri",
      "leadStatus": "Open Leads",
      "leadSubStatus": "Not Contacted",
      "createdTime": "2026-02-23T10:57:43+05:30",
      "called": false,
      "modifiedTime": "2026-02-23T10:57:43+05:30"
    },
    {
      "name": "Incoming Call Lead",
      "phone": "9629333344",
      "owner": "Anuj Polladia",
      "leadStatus": "Contacted",
      "leadSubStatus": "Call Back Later",
      "createdTime": "2026-02-23T10:53:13+05:30",
      "called": true,
      "modifiedTime": "2026-02-23T16:02:13+05:30"
    },
    {
      "name": "Sonia",
      "phone": "9633613796",
      "owner": "Rajeswari R",
      "leadStatus": "Rejected",
      "leadSubStatus": "Out Of Service Area",
      "createdTime": "2026-02-23T10:53:13+05:30",
      "called": true,
      "modifiedTime": "2026-02-23T12:12:00+05:30"
    },
    {
      "name": "ELV Helath care polcyclincis",
      "phone": "8971963102",
      "owner": "Rani KJ",
      "leadStatus": "Rejected",
      "leadSubStatus": "Just Enquiring",
      "createdTime": "2026-02-23T10:51:43+05:30",
      "called": true,
      "modifiedTime": "2026-02-23T15:43:48+05:30"
    }
  ],
  "overdueFollowups": [
    {
      "name": "Ullas",
      "owner": "Pardeep Kumar",
      "phone": "7892587433",
      "minutesSinceCreated": 81
    },
    {
      "name": "Anish V",
      "owner": "Reshma Reddy",
      "phone": "9535038379",
      "minutesSinceCreated": 153
    },
    {
      "name": "Architha K P",
      "owner": "Himasri",
      "phone": "8217397896",
      "minutesSinceCreated": 157
    },
    {
      "name": "HARISH Dasappa",
      "owner": "Rani KJ",
      "phone": "08762093372",
      "minutesSinceCreated": 159
    },
    {
      "name": "Sameer",
      "owner": "Rith Tamang",
      "phone": "6389789268",
      "minutesSinceCreated": 306
    },
    {
      "name": "Chetali samant",
      "owner": "Pardeep Kumar",
      "phone": "09482689840",
      "minutesSinceCreated": 336
    },
    {
      "name": "Janakiram reddy",
      "owner": "Pardeep Kumar",
      "phone": "8686386564",
      "minutesSinceCreated": 450
    },
    {
      "name": "Sneha",
      "owner": "Pardeep Kumar",
      "phone": "6001856775",
      "minutesSinceCreated": 685
    },
    {
      "name": "Suresh",
      "owner": "Pardeep Kumar",
      "phone": "7760498300",
      "minutesSinceCreated": 777
    },
    {
      "name": "Archana",
      "owner": "Pardeep Kumar",
      "phone": "09573680660",
      "minutesSinceCreated": 906
    },
    {
      "name": "Smruti Mishra",
      "owner": "Rani KJ",
      "phone": "8147062129",
      "minutesSinceCreated": 1381
    },
    {
      "name": "H Ramakrishnaiah",
      "owner": "Pardeep Kumar",
      "phone": "9538154455",
      "minutesSinceCreated": 1504
    },
    {
      "name": "Praveen",
      "owner": "Pardeep Kumar",
      "phone": "9063086861",
      "minutesSinceCreated": 1515
    },
    {
      "name": "Bhuvan",
      "owner": "Himasri",
      "phone": "9886983427",
      "minutesSinceCreated": 1538
    },
    {
      "name": "Udaya Kumar A",
      "owner": "Anuj Polladia",
      "phone": "9886918151",
      "minutesSinceCreated": 1608
    },
    {
      "name": "Sameer Ali Waheed",
      "owner": "Himasri",
      "phone": "09980504832",
      "minutesSinceCreated": 1659
    }
  ],
  "ownerStats": [
    {
      "owner": "Neha Aziz",
      "todaysLeads": 16,
      "calledLeads": 16,
      "todaysDeals": 4,
      "totalTasks": 21,
      "completedTasks": 3,
      "leadToDealConversionPercent": 25,
      "taskCompletionPercent": 14.3,
      "retentionPercent": 100
    },
    {
      "owner": "Rith Tamang",
      "todaysLeads": 14,
      "calledLeads": 13,
      "todaysDeals": 11,
      "totalTasks": 11,
      "completedTasks": 6,
      "leadToDealConversionPercent": 78.6,
      "taskCompletionPercent": 54.5,
      "retentionPercent": 92.9
    },
    {
      "owner": "Himasri",
      "todaysLeads": 13,
      "calledLeads": 12,
      "todaysDeals": 6,
      "totalTasks": 8,
      "completedTasks": 0,
      "leadToDealConversionPercent": 46.2,
      "taskCompletionPercent": 0,
      "retentionPercent": 92.3
    },
    {
      "owner": "Rani KJ",
      "todaysLeads": 11,
      "calledLeads": 9,
      "todaysDeals": 8,
      "totalTasks": 3,
      "completedTasks": 3,
      "leadToDealConversionPercent": 72.7,
      "taskCompletionPercent": 100,
      "retentionPercent": 81.8
    },
    {
      "owner": "Shahin BR",
      "todaysLeads": 9,
      "calledLeads": 9,
      "todaysDeals": 6,
      "totalTasks": 8,
      "completedTasks": 1,
      "leadToDealConversionPercent": 66.7,
      "taskCompletionPercent": 12.5,
      "retentionPercent": 100
    },
    {
      "owner": "Pardeep Kumar",
      "todaysLeads": 6,
      "calledLeads": 1,
      "todaysDeals": 0,
      "totalTasks": 0,
      "completedTasks": 0,
      "leadToDealConversionPercent": 0,
      "taskCompletionPercent": 0,
      "retentionPercent": 16.7
    },
    {
      "owner": "Reshma Reddy",
      "todaysLeads": 6,
      "calledLeads": 5,
      "todaysDeals": 2,
      "totalTasks": 7,
      "completedTasks": 0,
      "leadToDealConversionPercent": 33.3,
      "taskCompletionPercent": 0,
      "retentionPercent": 83.3
    },
    {
      "owner": "Anuj Polladia",
      "todaysLeads": 5,
      "calledLeads": 5,
      "todaysDeals": 6,
      "totalTasks": 1,
      "completedTasks": 0,
      "leadToDealConversionPercent": 120,
      "taskCompletionPercent": 0,
      "retentionPercent": 100
    },
    {
      "owner": "Vineeth Wankhade",
      "todaysLeads": 3,
      "calledLeads": 3,
      "todaysDeals": 0,
      "totalTasks": 0,
      "completedTasks": 0,
      "leadToDealConversionPercent": 0,
      "taskCompletionPercent": 0,
      "retentionPercent": 100
    },
    {
      "owner": "Amala",
      "todaysLeads": 2,
      "calledLeads": 2,
      "todaysDeals": 0,
      "totalTasks": 0,
      "completedTasks": 0,
      "leadToDealConversionPercent": 0,
      "taskCompletionPercent": 0,
      "retentionPercent": 100
    },
    {
      "owner": "Rajeswari R",
      "todaysLeads": 2,
      "calledLeads": 2,
      "todaysDeals": 0,
      "totalTasks": 17,
      "completedTasks": 0,
      "leadToDealConversionPercent": 0,
      "taskCompletionPercent": 0,
      "retentionPercent": 100
    }
  ]
}